test/counter.vhdl
library ieee;
use ieee.std_logic_1164.all;
use ieee.std_logic_unsigned.all;

entity counter is
port (
  clk:    in  std_logic;
  n_rst:  in  std_logic;
  cout:   out std_logic_vector (7 downto 0)
);
end entity;

architecture behaviour of counter is
  signal cnt: std_logic_vector (7 downto 0);
begin
  process (clk, n_rst)
  begin
    if n_rst = '0' then
      cnt <= (others => '0');
    elsif rising_edge(clk) then
      cnt <= cnt + 1;
    end if;
  end process;

  cout <= cnt;
end architecture;

test/counter.test.vhdl
library ieee;
use ieee.std_logic_1164.all;
use ieee.std_logic_unsigned.all;

entity counter_tb is
end entity;

architecture testbench of counter_tb is
  component counter
    port(
      clk:    in  std_logic;
      n_rst:  in  std_logic;
      cout:   out std_logic_vector (7 downto 0)
    );
  end component;

  signal  clk:    std_logic;
  signal  n_rst:  std_logic;
  signal  cout:   std_logic_vector (7 downto 0);

begin
  dut: counter port map (clk, n_rst, cout);

  process
  begin
    clk <= '0';
    wait for 5 ns;
    clk <= '1';
    wait for 5 ns;
  end process;

  process
  begin
    n_rst <= '0';
    wait for 10 ns;
    n_rst <= '1';
    wait for 250 ns;
  end process;
end;

test/counter_tb.vcd
$date
  Fri Mar 11 23:14:55 2022
$end
$version
  GHDL v0
$end
$timescale
  1 fs
$end
$scope module standard $end
$upscope $end
$scope module textio $end
$upscope $end
$scope module std_logic_1164 $end
$upscope $end
$scope module std_logic_arith $end
$upscope $end
$scope module std_logic_unsigned $end
$upscope $end
$scope module counter_tb $end
$var reg 1 ! clk $end
$var reg 1 " n_rst $end
$var reg 8 # cout[7:0] $end
$scope module dut $end
$var reg 1 $ clk $end
$var reg 1 % n_rst $end
$var reg 8 & cout[7:0] $end
$var reg 8 ' cnt[7:0] $end
$upscope $end
$upscope $end
$enddefinitions $end
#0
0!
0"
b00000000 #
0$
0%
b00000000 &
b00000000 '
#5000000
1!
1$
#10000000
0!
1"
0$
1%
#15000000
1!
b00000001 #
1$
b00000001 &
b00000001 '
#20000000
0!
0$
#25000000
1!
b00000010 #
1$
b00000010 &
b00000010 '
#30000000
0!
0$
#35000000
1!
b00000011 #
1$
b00000011 &
b00000011 '
#40000000
0!
0$
#45000000
1!
b00000100 #
1$
b00000100 &
b00000100 '
#50000000
0!
0$
#55000000
1!
b00000101 #
1$
b00000101 &
b00000101 '
#60000000
0!
0$
#65000000
1!
b00000110 #
1$
b00000110 &
b00000110 '
#70000000
0!
0$
#75000000
1!
b00000111 #
1$
b00000111 &
b00000111 '
#80000000
0!
0$
#85000000
1!
b00001000 #
1$
b00001000 &
b00001000 '
#90000000
0!
0$
#95000000
1!
b00001001 #
1$
b00001001 &
b00001001 '
#100000000
0!
0$
#105000000
1!
b00001010 #
1$
b00001010 &
b00001010 '
#110000000
0!
0$
#115000000
1!
b00001011 #
1$
b00001011 &
b00001011 '
#120000000
0!
0$
#125000000
1!
b00001100 #
1$
b00001100 &
b00001100 '
#130000000
0!
0$
#135000000
1!
b00001101 #
1$
b00001101 &
b00001101 '
#140000000
0!
0$
#145000000
1!
b00001110 #
1$
b00001110 &
b00001110 '
#150000000
0!
0$
#155000000
1!
b00001111 #
1$
b00001111 &
b00001111 '
#160000000
0!
0$
#165000000
1!
b00010000 #
1$
b00010000 &
b00010000 '
#170000000
0!
0$
#175000000
1!
b00010001 #
1$
b00010001 &
b00010001 '
#180000000
0!
0$
#185000000
1!
b00010010 #
1$
b00010010 &
b00010010 '
#190000000
0!
0$
#195000000
1!
b00010011 #
1$
b00010011 &
b00010011 '
#200000000
0!
0$
#205000000
1!
b00010100 #
1$
b00010100 &
b00010100 '
#210000000
0!
0$
#215000000
1!
b00010101 #
1$
b00010101 &
b00010101 '
#220000000
0!
0$
#225000000
1!
b00010110 #
1$
b00010110 &
b00010110 '
#230000000
0!
0$
#235000000
1!
b00010111 #
1$
b00010111 &
b00010111 '
#240000000
0!
0$
#245000000
1!
b00011000 #
1$
b00011000 &
b00011000 '
#250000000
0!
0$
#255000000
1!
b00011001 #
1$
b00011001 &
b00011001 '
#260000000
0!
0"
b00000000 #
0$
0%
b00000000 &
b00000000 '
#265000000
1!
1$
#270000000
0!
1"
0$
1%
#275000000
1!
b00000001 #
1$
b00000001 &
b00000001 '
#280000000
0!
0$
#285000000
1!
b00000010 #
1$
b00000010 &
b00000010 '
#290000000
0!
0$
#295000000
1!
b00000011 #
1$
b00000011 &
b00000011 '
#300000000
0!
0$
#305000000
1!
b00000100 #
1$
b00000100 &
b00000100 '
#310000000
0!
0$
#315000000
1!
b00000101 #
1$
b00000101 &
b00000101 '
#320000000
0!
0$
#325000000
1!
b00000110 #
1$
b00000110 &
b00000110 '
#330000000
0!
0$
#335000000
1!
b00000111 #
1$
b00000111 &
b00000111 '
#340000000
0!
0$
#345000000
1!
b00001000 #
1$
b00001000 &
b00001000 '
#350000000
0!
0$
#355000000
1!
b00001001 #
1$
b00001001 &
b00001001 '
#360000000
0!
0$
#365000000
1!
b00001010 #
1$
b00001010 &
b00001010 '
#370000000
0!
0$
#375000000
1!
b00001011 #
1$
b00001011 &
b00001011 '
#380000000
0!
0$
#385000000
1!
b00001100 #
1$
b00001100 &
b00001100 '
#390000000
0!
0$
#395000000
1!
b00001101 #
1$
b00001101 &
b00001101 '
#400000000
0!
0$
#405000000
1!
b00001110 #
1$
b00001110 &
b00001110 '
#410000000
0!
0$
#415000000
1!
b00001111 #
1$
b00001111 &
b00001111 '
#420000000
0!
0$
#425000000
1!
b00010000 #
1$
b00010000 &
b00010000 '
#430000000
0!
0$
#435000000
1!
b00010001 #
1$
b00010001 &
b00010001 '
#440000000
0!
0$
#445000000
1!
b00010010 #
1$
b00010010 &
b00010010 '
#450000000
0!
0$
#455000000
1!
b00010011 #
1$
b00010011 &
b00010011 '
#460000000
0!
0$
#465000000
1!
b00010100 #
1$
b00010100 &
b00010100 '
#470000000
0!
0$
#475000000
1!
b00010101 #
1$
b00010101 &
b00010101 '
#480000000
0!
0$
#485000000
1!
b00010110 #
1$
b00010110 &
b00010110 '
#490000000
0!
0$
#495000000
1!
b00010111 #
1$
b00010111 &
b00010111 '
#500000000
0!
0$
#505000000
1!
b00011000 #
1$
b00011000 &
b00011000 '
#510000000
0!
0$
#515000000
1!
b00011001 #
1$
b00011001 &
b00011001 '
#520000000
0!
0"
b00000000 #
0$
0%
b00000000 &
b00000000 '
#525000000
1!
1$
#530000000
0!
1"
0$
1%
#535000000
1!
b00000001 #
1$
b00000001 &
b00000001 '
#540000000
0!
0$
#545000000
1!
b00000010 #
1$
b00000010 &
b00000010 '
#550000000
0!
0$
#555000000
1!
b00000011 #
1$
b00000011 &
b00000011 '
#560000000
0!
0$
#565000000
1!
b00000100 #
1$
b00000100 &
b00000100 '
#570000000
0!
0$
#575000000
1!
b00000101 #
1$
b00000101 &
b00000101 '
#580000000
0!
0$
#585000000
1!
b00000110 #
1$
b00000110 &
b00000110 '
#590000000
0!
0$
#595000000
1!
b00000111 #
1$
b00000111 &
b00000111 '
#600000000
0!
0$
#605000000
1!
b00001000 #
1$
b00001000 &
b00001000 '
#610000000
0!
0$
#615000000
1!
b00001001 #
1$
b00001001 &
b00001001 '
#620000000
0!
0$
#625000000
1!
b00001010 #
1$
b00001010 &
b00001010 '
#630000000
0!
0$
#635000000
1!
b00001011 #
1$
b00001011 &
b00001011 '
#640000000
0!
0$
#645000000
1!
b00001100 #
1$
b00001100 &
b00001100 '
#650000000
0!
0$
#655000000
1!
b00001101 #
1$
b00001101 &
b00001101 '
#660000000
0!
0$
#665000000
1!
b00001110 #
1$
b00001110 &
b00001110 '
#670000000
0!
0$
#675000000
1!
b00001111 #
1$
b00001111 &
b00001111 '
#680000000
0!
0$
#685000000
1!
b00010000 #
1$
b00010000 &
b00010000 '
#690000000
0!
0$
#695000000
1!
b00010001 #
1$
b00010001 &
b00010001 '
#700000000
0!
0$
#705000000
1!
b00010010 #
1$
b00010010 &
b00010010 '
#710000000
0!
0$
#715000000
1!
b00010011 #
1$
b00010011 &
b00010011 '
#720000000
0!
0$
#725000000
1!
b00010100 #
1$
b00010100 &
b00010100 '
#730000000
0!
0$
#735000000
1!
b00010101 #
1$
b00010101 &
b00010101 '
#740000000
0!
0$
#745000000
1!
b00010110 #
1$
b00010110 &
b00010110 '
#750000000
0!
0$
#755000000
1!
b00010111 #
1$
b00010111 &
b00010111 '
#760000000
0!
0$
#765000000
1!
b00011000 #
1$
b00011000 &
b00011000 '
#770000000
0!
0$
#775000000
1!
b00011001 #
1$
b00011001 &
b00011001 '
#780000000
0!
0"
b00000000 #
0$
0%
b00000000 &
b00000000 '
#785000000
1!
1$
#790000000
0!
1"
0$
1%
#795000000
1!
b00000001 #
1$
b00000001 &
b00000001 '
#800000000
0!
0$
#805000000
1!
b00000010 #
1$
b00000010 &
b00000010 '
#810000000
0!
0$
#815000000
1!
b00000011 #
1$
b00000011 &
b00000011 '
#820000000
0!
0$
#825000000
1!
b00000100 #
1$
b00000100 &
b00000100 '
#830000000
0!
0$
#835000000
1!
b00000101 #
1$
b00000101 &
b00000101 '
#840000000
0!
0$
#845000000
1!
b00000110 #
1$
b00000110 &
b00000110 '
#850000000
0!
0$
#855000000
1!
b00000111 #
1$
b00000111 &
b00000111 '
#860000000
0!
0$
#865000000
1!
b00001000 #
1$
b00001000 &
b00001000 '
#870000000
0!
0$
#875000000
1!
b00001001 #
1$
b00001001 &
b00001001 '
#880000000
0!
0$
#885000000
1!
b00001010 #
1$
b00001010 &
b00001010 '
#890000000
0!
0$
#895000000
1!
b00001011 #
1$
b00001011 &
b00001011 '
#900000000
0!
0$
#905000000
1!
b00001100 #
1$
b00001100 &
b00001100 '
#910000000
0!
0$
#915000000
1!
b00001101 #
1$
b00001101 &
b00001101 '
#920000000
0!
0$
#925000000
1!
b00001110 #
1$
b00001110 &
b00001110 '
#930000000
0!
0$
#935000000
1!
b00001111 #
1$
b00001111 &
b00001111 '
#940000000
0!
0$
#945000000
1!
b00010000 #
1$
b00010000 &
b00010000 '
#950000000
0!
0$
#955000000
1!
b00010001 #
1$
b00010001 &
b00010001 '
#960000000
0!
0$
#965000000
1!
b00010010 #
1$
b00010010 &
b00010010 '
#970000000
0!
0$
#975000000
1!
b00010011 #
1$
b00010011 &
b00010011 '
#980000000
0!
0$
#985000000
1!
b00010100 #
1$
b00010100 &
b00010100 '
#990000000
0!
0$
#995000000
1!
b00010101 #
1$
b00010101 &
b00010101 '
