decoder/dec3x8_conditional.vhd
library IEEE;
use IEEE.STD_LOGIC_1164.ALL;
use IEEE.STD_LOGIC_ARITH.ALL;
use IEEE.STD_LOGIC_UNSIGNED.ALL;

entity dec3x8_conditional is
port(x:in STD_LOGIC_VECTOR(2 downto 0);
     y:out STD_LOGIC_VECTOR(7 downto 0));

end dec3x8_conditional;

architecture behavioral of dec3x8_conditional is
begin
  y  <=        "00000001" when (x="000") else
               "00000010" when (x="001") else
               "00000100" when (x="010") else
               "00001000" when (x="011") else
               "00010000" when (x="100") else
               "00100000" when (x="101") else
               "01000000" when (x="110") else
               "10000000" when (x="111") else
               "XXXXXXXX";
end architecture;

decoder/dec3x8_conditional_test.vhd
library IEEE;
use IEEE.STD_LOGIC_1164.ALL;


--this is how entity for your test bench code has to be declared.
entity dec3x8_conditional_test is
end dec3x8_conditional_test;

architecture behavior of dec3x8_conditional_test is
--signal declarations.
signal input : std_logic_vector(2 downto 0) :=(others => '0');
signal output :  std_logic_vector(7 downto 0) :=(others => '0');

begin
--entity instantiation
UUT : entity work.dec3x8_conditional port map(input,output);

--definition of simulation process
tb : process 
begin
input<="000";  --input = 0.
wait for 2 ns;
input<="001";   --input = 1.
wait for 2 ns;
input<="010";   --input = 2.
wait for 2 ns;
input<="011";   --input = 3.
wait for 2 ns;
input<="100";   --input = 4.
wait for 2 ns;
input<="101";   --input = 5.
wait for 2 ns;
input<="110";   --input = 6.
wait for 2 ns;
input<="111";   --input = 7.
wait;
end process tb;

end;

waves/dec3x8_conditional_test.vcd
$date
  Sun Mar 13 00:14:50 2022
$end
$version
  GHDL v0
$end
$timescale
  1 fs
$end
$scope module standard $end
$upscope $end
$scope module textio $end
$upscope $end
$scope module std_logic_1164 $end
$upscope $end
$scope module std_logic_arith $end
$upscope $end
$scope module std_logic_unsigned $end
$upscope $end
$scope module dec3x8_conditional_test $end
$var reg 3 ! input[2:0] $end
$var reg 8 " output[7:0] $end
$scope module uut $end
$var reg 3 # x[2:0] $end
$var reg 8 $ y[7:0] $end
$upscope $end
$upscope $end
$enddefinitions $end
#0
b000 !
b00000001 "
b000 #
b00000001 $
#2000000
b001 !
b00000010 "
b001 #
b00000010 $
#4000000
b010 !
b00000100 "
b010 #
b00000100 $
#6000000
b011 !
b00001000 "
b011 #
b00001000 $
#8000000
b100 !
b00010000 "
b100 #
b00010000 $
#10000000
b101 !
b00100000 "
b101 #
b00100000 $
#12000000
b110 !
b01000000 "
b110 #
b01000000 $
#14000000
b111 !
b10000000 "
b111 #
b10000000 $
