decoder/dec3x8_sel.vhd
LIBRARY IEEE;
USE IEEE.STD_LOGIC_1164.ALL;

ENTITY dec3x8_sel IS
      PORT (
            input : IN STD_LOGIC_VECTOR(2 DOWNTO 0); --3 bit input
            output : OUT STD_LOGIC_VECTOR(7 DOWNTO 0) -- 8 bit ouput
      );
END dec3x8_sel;
ARCHITECTURE Behavioral OF dec3x8_sel IS

BEGIN

      WITH input SELECT
            output <=
            TRANSPORT "00000001" AFTER 50 ns WHEN "000",
            "00000010" AFTER 50 ns WHEN "001",
            "00000100" WHEN "010",
            "00001000" WHEN "011",
            "00010000" WHEN "100",
            "00100000" WHEN "101",
            "01000000" WHEN "110",
            "10000000" WHEN "111",
            "00000000" WHEN OTHERS;
END Behavioral;

decoder/dec3x8_sel_test.vhd
LIBRARY IEEE;
USE IEEE.STD_LOGIC_1164.ALL;
--this is how entity for your test bench code has to be declared.
ENTITY dec3x8_sel_test IS
END dec3x8_sel_test;

ARCHITECTURE behavior OF dec3x8_sel_test IS
    --signal declarations.
    SIGNAL input : STD_LOGIC_VECTOR(2 DOWNTO 0) := (OTHERS => '0');
    SIGNAL output : STD_LOGIC_VECTOR(7 DOWNTO 0) := (OTHERS => '0');

BEGIN
    --entity instantiation
    UUT : ENTITY work.dec3x8_sel PORT MAP(input, output);

    --definition of simulation process
    tb : PROCESS
    BEGIN
        input <= "000"; --input = 0.
        WAIT FOR 100 ns;
        input <= "001"; --input = 1.
        WAIT FOR 30 ns;
        input <= "000"; --input = 1.
        WAIT FOR 20 ns;

        input <= "000"; --input = 1.
        WAIT FOR 100 ns;

        input <= "001"; --input = 1.
        WAIT FOR 100 ns;
        input <= "000";
        WAIT FOR 30 ns;
        input <= "001";
        WAIT FOR 20 ns;
    END PROCESS tb;

END;

waves/dec3x8_sel_test.vcd
$date
  Mon Apr 11 22:37:52 2022
$end
$version
  GHDL v0
$end
$timescale
  1 fs
$end
$scope module standard $end
$upscope $end
$scope module textio $end
$upscope $end
$scope module std_logic_1164 $end
$upscope $end
$scope module dec3x8_sel_test $end
$var reg 3 ! input[2:0] $end
$var reg 8 " output[7:0] $end
$scope module uut $end
$var reg 3 # input[2:0] $end
$var reg 8 $ output[7:0] $end
$upscope $end
$upscope $end
$enddefinitions $end
#0
b000 !
bUUUUUUUU "
b000 #
bUUUUUUUU $
#50000000
b00000001 "
b00000001 $
#100000000
b001 !
b001 #
#130000000
b000 !
b000 #
#150000000
b00000010 "
b00000010 $
#180000000
b00000001 "
b00000001 $
#250000000
b001 !
b001 #
#300000000
b00000010 "
b00000010 $
#350000000
b000 !
b000 #
#380000000
b001 !
b001 #
#400000000
b000 !
b00000001 "
b000 #
b00000001 $
#430000000
b00000010 "
b00000010 $
#450000000
b00000001 "
b00000001 $
#500000000
b001 !
b001 #
#530000000
b000 !
b000 #
#550000000
b00000010 "
b00000010 $
#580000000
b00000001 "
b00000001 $
#650000000
b001 !
b001 #
#700000000
b00000010 "
b00000010 $
#750000000
b000 !
b000 #
#780000000
b001 !
b001 #
#800000000
b000 !
b00000001 "
b000 #
b00000001 $
#830000000
b00000010 "
b00000010 $
#850000000
b00000001 "
b00000001 $
#900000000
b001 !
b001 #
#930000000
b000 !
b000 #
#950000000
b00000010 "
b00000010 $
#980000000
b00000001 "
b00000001 $
