demux/demux1x32.vhd
LIBRARY ieee;
USE ieee.std_logic_1164.ALL;
USE ieee.numeric_std.ALL;

ENTITY Demux1x32 IS
    PORT (
        x : IN STD_LOGIC;
        sel : IN STD_LOGIC_VECTOR(4 DOWNTO 0);
        y : OUT STD_LOGIC_VECTOR(31 DOWNTO 0)
    );
END Demux1x32;

ARCHITECTURE rtl OF Demux1x32 IS

BEGIN

    y(0) <= x when (sel = "00000") else '0';
    y(1) <= x when (sel = "00001") else '0';
    y(2) <= x when (sel = "00010") else '0';
    y(3) <= x when (sel = "00011") else '0';
    y(4) <= x when (sel = "00100") else '0';
    y(5) <= x when (sel = "00101") else '0';
    y(6) <= x when (sel = "00110") else '0';
    y(7) <= x when (sel = "00111") else '0';
    y(8) <= x when (sel = "01000") else '0';
    y(9) <= x when (sel = "01001") else '0';
    y(10) <= x when (sel = "01010") else '0';
    y(11) <= x when (sel = "01011") else '0';
    y(12) <= x when (sel = "01100") else '0';
    y(13) <= x when (sel = "01101") else '0';
    y(14) <= x when (sel = "01110") else '0';
    y(15) <= x when (sel = "01111") else '0';
    y(16) <= x when (sel = "10000") else '0';
    y(17) <= x when (sel = "10001") else '0';
    y(18) <= x when (sel = "10010") else '0';
    y(19) <= x when (sel = "10011") else '0';
    y(20) <= x when (sel = "10100") else '0';
    y(21) <= x when (sel = "10101") else '0';
    y(22) <= x when (sel = "10110") else '0';
    y(23) <= x when (sel = "10111") else '0';
    y(24) <= x when (sel = "11000") else '0';
    y(25) <= x when (sel = "11001") else '0';
    y(26) <= x when (sel = "11010") else '0';
    y(27) <= x when (sel = "11011") else '0';
    y(28) <= x when (sel = "11100") else '0';
    y(29) <= x when (sel = "11101") else '0';
    y(30) <= x when (sel = "11110") else '0';
    y(31) <= x when (sel = "11111") else '0';
    

END ARCHITECTURE;

demux/demux1x32_test.vhdl
LIBRARY IEEE;
USE IEEE.STD_LOGIC_1164.ALL;
USE IEEE.STD_LOGIC_ARITH.ALL;
USE IEEE.STD_LOGIC_UNSIGNED.ALL;
USE IEEE.NUMERIC_STD.ALL;

--this is how entity for your test bench code has to be declared.
ENTITY demux1x32_test IS
END demux1x32_test;

ARCHITECTURE behavior OF demux1x32_test IS
    --signal declarations.
    -- x : IN STD_LOGIC;
    -- sel : IN STD_LOGIC_VECTOR(4 DOWNTO 0);
    -- y : OUT STD_LOGIC_VECTOR(31 DOWNTO 0)

    SIGNAL x : STD_LOGIC;
    SIGNAL sel : STD_LOGIC_VECTOR(4 DOWNTO 0) := (OTHERS => '0');
    SIGNAL y : STD_LOGIC_VECTOR(31 DOWNTO 0) := (OTHERS => '0');

BEGIN
    --entity instantiation
    UUT : ENTITY work.demux1x32 PORT MAP(x, sel, y);

    --definition of simulation process
    tb : PROCESS
    BEGIN
        FOR j IN STD_LOGIC RANGE '0' TO '1' LOOP
            x <= j;
            FOR i IN 0 TO 2 ** sel'length - 1 LOOP
                sel <= STD_LOGIC_VECTOR(to_unsigned(i, sel'length));
                WAIT FOR 2 ns;
            END LOOP;
        END LOOP;
    END PROCESS tb;
END;

waves/demux1x32_test.vcd
$date
  Sat Mar 12 23:50:13 2022
$end
$version
  GHDL v0
$end
$timescale
  1 fs
$end
$scope module standard $end
$upscope $end
$scope module textio $end
$upscope $end
$scope module std_logic_1164 $end
$upscope $end
$scope module std_logic_arith $end
$upscope $end
$scope module std_logic_unsigned $end
$upscope $end
$scope module numeric_std $end
$upscope $end
$scope module demux1x32_test $end
$var reg 1 ! x $end
$var reg 5 " sel[4:0] $end
$var reg 32 # y[31:0] $end
$scope module uut $end
$var reg 1 $ x $end
$var reg 5 % sel[4:0] $end
$var reg 32 & y[31:0] $end
$upscope $end
$upscope $end
$enddefinitions $end
#0
0!
b00000 "
b00000000000000000000000000000000 #
0$
b00000 %
b00000000000000000000000000000000 &
#2000000
b00001 "
b00001 %
#4000000
b00010 "
b00010 %
#6000000
b00011 "
b00011 %
#8000000
b00100 "
b00100 %
#10000000
b00101 "
b00101 %
#12000000
b00110 "
b00110 %
#14000000
b00111 "
b00111 %
#16000000
b01000 "
b01000 %
#18000000
b01001 "
b01001 %
#20000000
b01010 "
b01010 %
#22000000
b01011 "
b01011 %
#24000000
b01100 "
b01100 %
#26000000
b01101 "
b01101 %
#28000000
b01110 "
b01110 %
#30000000
b01111 "
b01111 %
#32000000
b10000 "
b10000 %
#34000000
b10001 "
b10001 %
#36000000
b10010 "
b10010 %
#38000000
b10011 "
b10011 %
#40000000
b10100 "
b10100 %
#42000000
b10101 "
b10101 %
#44000000
b10110 "
b10110 %
#46000000
b10111 "
b10111 %
#48000000
b11000 "
b11000 %
#50000000
b11001 "
b11001 %
#52000000
b11010 "
b11010 %
#54000000
b11011 "
b11011 %
#56000000
b11100 "
b11100 %
#58000000
b11101 "
b11101 %
#60000000
b11110 "
b11110 %
#62000000
b11111 "
b11111 %
#64000000
1!
b00000 "
b00000000000000000000000000000001 #
1$
b00000 %
b00000000000000000000000000000001 &
#66000000
b00001 "
b00000000000000000000000000000010 #
b00001 %
b00000000000000000000000000000010 &
#68000000
b00010 "
b00000000000000000000000000000100 #
b00010 %
b00000000000000000000000000000100 &
#70000000
b00011 "
b00000000000000000000000000001000 #
b00011 %
b00000000000000000000000000001000 &
#72000000
b00100 "
b00000000000000000000000000010000 #
b00100 %
b00000000000000000000000000010000 &
#74000000
b00101 "
b00000000000000000000000000100000 #
b00101 %
b00000000000000000000000000100000 &
#76000000
b00110 "
b00000000000000000000000001000000 #
b00110 %
b00000000000000000000000001000000 &
#78000000
b00111 "
b00000000000000000000000010000000 #
b00111 %
b00000000000000000000000010000000 &
#80000000
b01000 "
b00000000000000000000000100000000 #
b01000 %
b00000000000000000000000100000000 &
#82000000
b01001 "
b00000000000000000000001000000000 #
b01001 %
b00000000000000000000001000000000 &
#84000000
b01010 "
b00000000000000000000010000000000 #
b01010 %
b00000000000000000000010000000000 &
#86000000
b01011 "
b00000000000000000000100000000000 #
b01011 %
b00000000000000000000100000000000 &
#88000000
b01100 "
b00000000000000000001000000000000 #
b01100 %
b00000000000000000001000000000000 &
#90000000
b01101 "
b00000000000000000010000000000000 #
b01101 %
b00000000000000000010000000000000 &
#92000000
b01110 "
b00000000000000000100000000000000 #
b01110 %
b00000000000000000100000000000000 &
#94000000
b01111 "
b00000000000000001000000000000000 #
b01111 %
b00000000000000001000000000000000 &
#96000000
b10000 "
b00000000000000010000000000000000 #
b10000 %
b00000000000000010000000000000000 &
#98000000
b10001 "
b00000000000000100000000000000000 #
b10001 %
b00000000000000100000000000000000 &
#100000000
b10010 "
b00000000000001000000000000000000 #
b10010 %
b00000000000001000000000000000000 &
#102000000
b10011 "
b00000000000010000000000000000000 #
b10011 %
b00000000000010000000000000000000 &
#104000000
b10100 "
b00000000000100000000000000000000 #
b10100 %
b00000000000100000000000000000000 &
#106000000
b10101 "
b00000000001000000000000000000000 #
b10101 %
b00000000001000000000000000000000 &
#108000000
b10110 "
b00000000010000000000000000000000 #
b10110 %
b00000000010000000000000000000000 &
#110000000
b10111 "
b00000000100000000000000000000000 #
b10111 %
b00000000100000000000000000000000 &
#112000000
b11000 "
b00000001000000000000000000000000 #
b11000 %
b00000001000000000000000000000000 &
#114000000
b11001 "
b00000010000000000000000000000000 #
b11001 %
b00000010000000000000000000000000 &
#116000000
b11010 "
b00000100000000000000000000000000 #
b11010 %
b00000100000000000000000000000000 &
#118000000
b11011 "
b00001000000000000000000000000000 #
b11011 %
b00001000000000000000000000000000 &
#120000000
b11100 "
b00010000000000000000000000000000 #
b11100 %
b00010000000000000000000000000000 &
#122000000
b11101 "
b00100000000000000000000000000000 #
b11101 %
b00100000000000000000000000000000 &
#124000000
b11110 "
b01000000000000000000000000000000 #
b11110 %
b01000000000000000000000000000000 &
#126000000
b11111 "
b10000000000000000000000000000000 #
b11111 %
b10000000000000000000000000000000 &
#128000000
0!
b00000 "
b00000000000000000000000000000000 #
0$
b00000 %
b00000000000000000000000000000000 &
