demux/demux1x8.vhd
LIBRARY ieee;
USE ieee.std_logic_1164.ALL;
USE ieee.numeric_std.ALL;

ENTITY Demux1x8 IS
    PORT (
        x : IN STD_LOGIC;
        sel : IN STD_LOGIC_VECTOR(2 DOWNTO 0);
        y : OUT STD_LOGIC_VECTOR(7 DOWNTO 0)
    );
END Demux1x8;

ARCHITECTURE rtl OF Demux1x8 IS

BEGIN
    WITH sel SELECT
        y(0) <= transport x after 20 ns WHEN "000" ,
        '0' WHEN OTHERS ;

    WITH sel SELECT
        y(1) <= x after 20 ns WHEN "001",
        '0' WHEN OTHERS;

    WITH sel SELECT
        y(2) <= x WHEN "010",
        '0' WHEN OTHERS;

    WITH sel SELECT
        y(3) <= x WHEN "011",
        '0' WHEN OTHERS;

    WITH sel SELECT
        y(4) <= x WHEN "100",
        '0' WHEN OTHERS;
        
    WITH sel SELECT
        y(5) <= x WHEN "101",
        '0' WHEN OTHERS;

    WITH sel SELECT
        y(6) <= x WHEN "110",
        '0' WHEN OTHERS;

    WITH sel SELECT
        y(7) <= x WHEN "111",
        '0' WHEN OTHERS;
END ARCHITECTURE;

demux/demux1x8_test.vhdl
LIBRARY IEEE;
USE IEEE.STD_LOGIC_1164.ALL;
USE IEEE.STD_LOGIC_ARITH.ALL;
USE IEEE.STD_LOGIC_UNSIGNED.ALL;
USE IEEE.NUMERIC_STD.ALL;

--this is how entity for your test bench code has to be declared.
ENTITY demux1x8_test IS
END demux1x8_test;

ARCHITECTURE behavior OF demux1x8_test IS
    --signal declarations.
    -- x : IN STD_LOGIC;
    -- sel : IN STD_LOGIC_VECTOR(4 DOWNTO 0);
    -- y : OUT STD_LOGIC_VECTOR(31 DOWNTO 0)

    SIGNAL x : STD_LOGIC;
    SIGNAL sel : STD_LOGIC_VECTOR(2 DOWNTO 0) := (OTHERS => '0');
    SIGNAL y : STD_LOGIC_VECTOR(7 DOWNTO 0) := (OTHERS => '0');

BEGIN
    --entity instantiation
    UUT : ENTITY work.demux1x8 PORT MAP(x, sel, y);

    --definition of simulation process
    tb : PROCESS
    begin
        x <= '0';
        wait for 100 ns;
        
        sel <= "000";
        x <= '1';
        wait for 50 ns;
        x <= '0';
        wait for 30 ns;
        x <= '1';
        wait for 20 ns;

        x <= '0';
        wait for 100 ns;

        sel <= "001";
        x <= '1';
        wait for 50 ns;
        x <= '0';
        wait for 30 ns;
        x <= '1';
        wait for 20 ns;

        x <= '0';
        wait for 100 ns;

    END PROCESS tb;
END;

waves/demux1x8_test.vcd
$date
  Mon Apr 11 22:30:08 2022
$end
$version
  GHDL v0
$end
$timescale
  1 fs
$end
$scope module standard $end
$upscope $end
$scope module textio $end
$upscope $end
$scope module std_logic_1164 $end
$upscope $end
$scope module std_logic_arith $end
$upscope $end
$scope module std_logic_unsigned $end
$upscope $end
$scope module numeric_std $end
$upscope $end
$scope module demux1x8_test $end
$var reg 1 ! x $end
$var reg 3 " sel[2:0] $end
$var reg 8 # y[7:0] $end
$scope module uut $end
$var reg 1 $ x $end
$var reg 3 % sel[2:0] $end
$var reg 8 & y[7:0] $end
$upscope $end
$upscope $end
$enddefinitions $end
#0
0!
b000 "
b0000000U #
0$
b000 %
b0000000U &
#20000000
b00000000 #
b00000000 &
#100000000
1!
1$
b00000000 &
#120000000
b00000001 #
b00000001 &
#150000000
0!
0$
b00000001 &
#170000000
b00000000 #
b00000000 &
#180000000
1!
1$
b00000000 &
#200000000
0!
b00000001 #
0$
b00000001 &
#220000000
b00000000 #
b00000000 &
#300000000
1!
b001 "
1$
b001 %
b00000000 &
#320000000
b00000010 #
b00000010 &
#350000000
0!
0$
b00000010 &
#370000000
b00000000 #
b00000000 &
#380000000
1!
1$
b00000000 &
#400000000
0!
b00000010 #
0$
b00000010 &
#420000000
b00000000 #
b00000000 &
