encoder/enc16x4.vhd
LIBRARY ieee;
USE IEEE.STD_LOGIC_1164.ALL;
USE IEEE.STD_LOGIC_ARITH.ALL;
USE IEEE.STD_LOGIC_UNSIGNED.ALL;

ENTITY enc16x4 IS
    PORT (
        x : IN STD_LOGIC_VECTOR(15 DOWNTO 0);
        y : OUT STD_LOGIC_VECTOR(3 DOWNTO 0));

END enc16x4;

ARCHITECTURE rtl OF enc16x4 IS

BEGIN
    y <= "0000" WHEN (x = "0000000000000001") ELSE
        "0001" WHEN (x = "0000000000000010") ELSE
        "0010" WHEN (x = "0000000000000100") ELSE
        "0011" WHEN (x = "0000000000001000") ELSE
        "0100" WHEN (x = "0000000000010000") ELSE
        "0101" WHEN (x = "0000000000100000") ELSE
        "0110" WHEN (x = "0000000001000000") ELSE
        "0111" WHEN (x = "0000000010000000") ELSE
        "1000" WHEN (x = "0000000100000000") ELSE
        "1001" WHEN (x = "0000001000000000") ELSE
        "1010" WHEN (x = "0000010000000000") ELSE
        "1011" WHEN (x = "0000100000000000") ELSE
        "1100" WHEN (x = "0001000000000000") ELSE
        "1101" WHEN (x = "0010000000000000") ELSE
        "1110" WHEN (x = "0100000000000000") ELSE
        "1111" WHEN (x = "1000000000000000");

END ARCHITECTURE;

encoder/enc16x4_test.vhd
LIBRARY IEEE;
USE IEEE.STD_LOGIC_1164.ALL;
USE IEEE.STD_LOGIC_ARITH.ALL;
USE IEEE.STD_LOGIC_UNSIGNED.ALL;
USE IEEE.NUMERIC_STD.ALL;

--this is how entity for your test bench code has to be declared.
ENTITY enc16x4_test IS
END enc16x4_test;

ARCHITECTURE behavior OF enc16x4_test IS
    --signal declarations.
    SIGNAL x : STD_LOGIC_VECTOR(15 DOWNTO 0) := (OTHERS => '0');
    SIGNAL y : STD_LOGIC_VECTOR(3 DOWNTO 0) := (OTHERS => '0');

BEGIN
    --entity instantiation
    UUT : ENTITY work.enc16x4 PORT MAP(x, y);

    --definition of simulation process
    tb : PROCESS
    BEGIN
        FOR j IN 0 TO 2 ** x'length - 1 LOOP
            x <= STD_LOGIC_VECTOR(to_unsigned(j, x'length));
            WAIT FOR 2 ns;
        END LOOP;
    END PROCESS tb;
END;

waves/enc16x4_test.vcd
$date
  Sun Mar 13 00:59:41 2022
$end
$version
  GHDL v0
$end
$timescale
  1 fs
$end
$scope module standard $end
$upscope $end
$scope module textio $end
$upscope $end
$scope module std_logic_1164 $end
$upscope $end
$scope module std_logic_arith $end
$upscope $end
$scope module std_logic_unsigned $end
$upscope $end
$scope module numeric_std $end
$upscope $end
$scope module enc16x4_test $end
$var reg 16 ! x[15:0] $end
$var reg 4 " y[3:0] $end
$scope module uut $end
$var reg 16 # x[15:0] $end
$var reg 4 $ y[3:0] $end
$upscope $end
$upscope $end
$enddefinitions $end
#0
b0000000000000000 !
bUUUU "
b0000000000000000 #
bUUUU $
#2000000
b0000000000000001 !
b0000 "
b0000000000000001 #
b0000 $
#4000000
b0000000000000010 !
b0001 "
b0000000000000010 #
b0001 $
#6000000
b0000000000000011 !
b0000000000000011 #
#8000000
b0000000000000100 !
b0010 "
b0000000000000100 #
b0010 $
#10000000
b0000000000000101 !
b0000000000000101 #
#12000000
b0000000000000110 !
b0000000000000110 #
#14000000
b0000000000000111 !
b0000000000000111 #
#16000000
b0000000000001000 !
b0011 "
b0000000000001000 #
b0011 $
#18000000
b0000000000001001 !
b0000000000001001 #
#20000000
b0000000000001010 !
b0000000000001010 #
#22000000
b0000000000001011 !
b0000000000001011 #
#24000000
b0000000000001100 !
b0000000000001100 #
#26000000
b0000000000001101 !
b0000000000001101 #
#28000000
b0000000000001110 !
b0000000000001110 #
#30000000
b0000000000001111 !
b0000000000001111 #
#32000000
b0000000000010000 !
b0100 "
b0000000000010000 #
b0100 $
#34000000
b0000000000010001 !
b0000000000010001 #
#36000000
b0000000000010010 !
b0000000000010010 #
#38000000
b0000000000010011 !
b0000000000010011 #
#40000000
b0000000000010100 !
b0000000000010100 #
#42000000
b0000000000010101 !
b0000000000010101 #
#44000000
b0000000000010110 !
b0000000000010110 #
#46000000
b0000000000010111 !
b0000000000010111 #
#48000000
b0000000000011000 !
b0000000000011000 #
#50000000
b0000000000011001 !
b0000000000011001 #
#52000000
b0000000000011010 !
b0000000000011010 #
#54000000
b0000000000011011 !
b0000000000011011 #
#56000000
b0000000000011100 !
b0000000000011100 #
#58000000
b0000000000011101 !
b0000000000011101 #
#60000000
b0000000000011110 !
b0000000000011110 #
#62000000
b0000000000011111 !
b0000000000011111 #
#64000000
b0000000000100000 !
b0101 "
b0000000000100000 #
b0101 $
#66000000
b0000000000100001 !
b0000000000100001 #
#68000000
b0000000000100010 !
b0000000000100010 #
#70000000
b0000000000100011 !
b0000000000100011 #
#72000000
b0000000000100100 !
b0000000000100100 #
#74000000
b0000000000100101 !
b0000000000100101 #
#76000000
b0000000000100110 !
b0000000000100110 #
#78000000
b0000000000100111 !
b0000000000100111 #
#80000000
b0000000000101000 !
b0000000000101000 #
#82000000
b0000000000101001 !
b0000000000101001 #
#84000000
b0000000000101010 !
b0000000000101010 #
#86000000
b0000000000101011 !
b0000000000101011 #
#88000000
b0000000000101100 !
b0000000000101100 #
#90000000
b0000000000101101 !
b0000000000101101 #
#92000000
b0000000000101110 !
b0000000000101110 #
#94000000
b0000000000101111 !
b0000000000101111 #
#96000000
b0000000000110000 !
b0000000000110000 #
#98000000
b0000000000110001 !
b0000000000110001 #
#100000000
b0000000000110010 !
b0000000000110010 #
#102000000
b0000000000110011 !
b0000000000110011 #
#104000000
b0000000000110100 !
b0000000000110100 #
#106000000
b0000000000110101 !
b0000000000110101 #
#108000000
b0000000000110110 !
b0000000000110110 #
#110000000
b0000000000110111 !
b0000000000110111 #
#112000000
b0000000000111000 !
b0000000000111000 #
#114000000
b0000000000111001 !
b0000000000111001 #
#116000000
b0000000000111010 !
b0000000000111010 #
#118000000
b0000000000111011 !
b0000000000111011 #
#120000000
b0000000000111100 !
b0000000000111100 #
#122000000
b0000000000111101 !
b0000000000111101 #
#124000000
b0000000000111110 !
b0000000000111110 #
#126000000
b0000000000111111 !
b0000000000111111 #
#128000000
b0000000001000000 !
b0110 "
b0000000001000000 #
b0110 $
#130000000
b0000000001000001 !
b0000000001000001 #
#132000000
b0000000001000010 !
b0000000001000010 #
#134000000
b0000000001000011 !
b0000000001000011 #
#136000000
b0000000001000100 !
b0000000001000100 #
#138000000
b0000000001000101 !
b0000000001000101 #
#140000000
b0000000001000110 !
b0000000001000110 #
#142000000
b0000000001000111 !
b0000000001000111 #
#144000000
b0000000001001000 !
b0000000001001000 #
#146000000
b0000000001001001 !
b0000000001001001 #
#148000000
b0000000001001010 !
b0000000001001010 #
#150000000
b0000000001001011 !
b0000000001001011 #
#152000000
b0000000001001100 !
b0000000001001100 #
#154000000
b0000000001001101 !
b0000000001001101 #
#156000000
b0000000001001110 !
b0000000001001110 #
#158000000
b0000000001001111 !
b0000000001001111 #
#160000000
b0000000001010000 !
b0000000001010000 #
#162000000
b0000000001010001 !
b0000000001010001 #
#164000000
b0000000001010010 !
b0000000001010010 #
#166000000
b0000000001010011 !
b0000000001010011 #
#168000000
b0000000001010100 !
b0000000001010100 #
#170000000
b0000000001010101 !
b0000000001010101 #
#172000000
b0000000001010110 !
b0000000001010110 #
#174000000
b0000000001010111 !
b0000000001010111 #
#176000000
b0000000001011000 !
b0000000001011000 #
#178000000
b0000000001011001 !
b0000000001011001 #
#180000000
b0000000001011010 !
b0000000001011010 #
#182000000
b0000000001011011 !
b0000000001011011 #
#184000000
b0000000001011100 !
b0000000001011100 #
#186000000
b0000000001011101 !
b0000000001011101 #
#188000000
b0000000001011110 !
b0000000001011110 #
#190000000
b0000000001011111 !
b0000000001011111 #
#192000000
b0000000001100000 !
b0000000001100000 #
#194000000
b0000000001100001 !
b0000000001100001 #
#196000000
b0000000001100010 !
b0000000001100010 #
#198000000
b0000000001100011 !
b0000000001100011 #
#200000000
b0000000001100100 !
b0000000001100100 #
#202000000
b0000000001100101 !
b0000000001100101 #
#204000000
b0000000001100110 !
b0000000001100110 #
#206000000
b0000000001100111 !
b0000000001100111 #
#208000000
b0000000001101000 !
b0000000001101000 #
#210000000
b0000000001101001 !
b0000000001101001 #
#212000000
b0000000001101010 !
b0000000001101010 #
#214000000
b0000000001101011 !
b0000000001101011 #
#216000000
b0000000001101100 !
b0000000001101100 #
#218000000
b0000000001101101 !
b0000000001101101 #
#220000000
b0000000001101110 !
b0000000001101110 #
#222000000
b0000000001101111 !
b0000000001101111 #
#224000000
b0000000001110000 !
b0000000001110000 #
#226000000
b0000000001110001 !
b0000000001110001 #
#228000000
b0000000001110010 !
b0000000001110010 #
#230000000
b0000000001110011 !
b0000000001110011 #
#232000000
b0000000001110100 !
b0000000001110100 #
#234000000
b0000000001110101 !
b0000000001110101 #
#236000000
b0000000001110110 !
b0000000001110110 #
#238000000
b0000000001110111 !
b0000000001110111 #
#240000000
b0000000001111000 !
b0000000001111000 #
#242000000
b0000000001111001 !
b0000000001111001 #
#244000000
b0000000001111010 !
b0000000001111010 #
#246000000
b0000000001111011 !
b0000000001111011 #
#248000000
b0000000001111100 !
b0000000001111100 #
#250000000
b0000000001111101 !
b0000000001111101 #
#252000000
b0000000001111110 !
b0000000001111110 #
#254000000
b0000000001111111 !
b0000000001111111 #
#256000000
b0000000010000000 !
b0111 "
b0000000010000000 #
b0111 $
#258000000
b0000000010000001 !
b0000000010000001 #
#260000000
b0000000010000010 !
b0000000010000010 #
#262000000
b0000000010000011 !
b0000000010000011 #
#264000000
b0000000010000100 !
b0000000010000100 #
#266000000
b0000000010000101 !
b0000000010000101 #
#268000000
b0000000010000110 !
b0000000010000110 #
#270000000
b0000000010000111 !
b0000000010000111 #
#272000000
b0000000010001000 !
b0000000010001000 #
#274000000
b0000000010001001 !
b0000000010001001 #
#276000000
b0000000010001010 !
b0000000010001010 #
#278000000
b0000000010001011 !
b0000000010001011 #
#280000000
b0000000010001100 !
b0000000010001100 #
#282000000
b0000000010001101 !
b0000000010001101 #
#284000000
b0000000010001110 !
b0000000010001110 #
#286000000
b0000000010001111 !
b0000000010001111 #
#288000000
b0000000010010000 !
b0000000010010000 #
#290000000
b0000000010010001 !
b0000000010010001 #
#292000000
b0000000010010010 !
b0000000010010010 #
#294000000
b0000000010010011 !
b0000000010010011 #
#296000000
b0000000010010100 !
b0000000010010100 #
#298000000
b0000000010010101 !
b0000000010010101 #
#300000000
b0000000010010110 !
b0000000010010110 #
#302000000
b0000000010010111 !
b0000000010010111 #
#304000000
b0000000010011000 !
b0000000010011000 #
#306000000
b0000000010011001 !
b0000000010011001 #
#308000000
b0000000010011010 !
b0000000010011010 #
#310000000
b0000000010011011 !
b0000000010011011 #
#312000000
b0000000010011100 !
b0000000010011100 #
#314000000
b0000000010011101 !
b0000000010011101 #
#316000000
b0000000010011110 !
b0000000010011110 #
#318000000
b0000000010011111 !
b0000000010011111 #
#320000000
b0000000010100000 !
b0000000010100000 #
#322000000
b0000000010100001 !
b0000000010100001 #
#324000000
b0000000010100010 !
b0000000010100010 #
#326000000
b0000000010100011 !
b0000000010100011 #
#328000000
b0000000010100100 !
b0000000010100100 #
#330000000
b0000000010100101 !
b0000000010100101 #
#332000000
b0000000010100110 !
b0000000010100110 #
#334000000
b0000000010100111 !
b0000000010100111 #
#336000000
b0000000010101000 !
b0000000010101000 #
#338000000
b0000000010101001 !
b0000000010101001 #
#340000000
b0000000010101010 !
b0000000010101010 #
#342000000
b0000000010101011 !
b0000000010101011 #
#344000000
b0000000010101100 !
b0000000010101100 #
#346000000
b0000000010101101 !
b0000000010101101 #
#348000000
b0000000010101110 !
b0000000010101110 #
#350000000
b0000000010101111 !
b0000000010101111 #
#352000000
b0000000010110000 !
b0000000010110000 #
#354000000
b0000000010110001 !
b0000000010110001 #
#356000000
b0000000010110010 !
b0000000010110010 #
#358000000
b0000000010110011 !
b0000000010110011 #
#360000000
b0000000010110100 !
b0000000010110100 #
#362000000
b0000000010110101 !
b0000000010110101 #
#364000000
b0000000010110110 !
b0000000010110110 #
#366000000
b0000000010110111 !
b0000000010110111 #
#368000000
b0000000010111000 !
b0000000010111000 #
#370000000
b0000000010111001 !
b0000000010111001 #
#372000000
b0000000010111010 !
b0000000010111010 #
#374000000
b0000000010111011 !
b0000000010111011 #
#376000000
b0000000010111100 !
b0000000010111100 #
#378000000
b0000000010111101 !
b0000000010111101 #
#380000000
b0000000010111110 !
b0000000010111110 #
#382000000
b0000000010111111 !
b0000000010111111 #
#384000000
b0000000011000000 !
b0000000011000000 #
#386000000
b0000000011000001 !
b0000000011000001 #
#388000000
b0000000011000010 !
b0000000011000010 #
#390000000
b0000000011000011 !
b0000000011000011 #
#392000000
b0000000011000100 !
b0000000011000100 #
#394000000
b0000000011000101 !
b0000000011000101 #
#396000000
b0000000011000110 !
b0000000011000110 #
#398000000
b0000000011000111 !
b0000000011000111 #
#400000000
b0000000011001000 !
b0000000011001000 #
#402000000
b0000000011001001 !
b0000000011001001 #
#404000000
b0000000011001010 !
b0000000011001010 #
#406000000
b0000000011001011 !
b0000000011001011 #
#408000000
b0000000011001100 !
b0000000011001100 #
#410000000
b0000000011001101 !
b0000000011001101 #
#412000000
b0000000011001110 !
b0000000011001110 #
#414000000
b0000000011001111 !
b0000000011001111 #
#416000000
b0000000011010000 !
b0000000011010000 #
#418000000
b0000000011010001 !
b0000000011010001 #
#420000000
b0000000011010010 !
b0000000011010010 #
#422000000
b0000000011010011 !
b0000000011010011 #
#424000000
b0000000011010100 !
b0000000011010100 #
#426000000
b0000000011010101 !
b0000000011010101 #
#428000000
b0000000011010110 !
b0000000011010110 #
#430000000
b0000000011010111 !
b0000000011010111 #
#432000000
b0000000011011000 !
b0000000011011000 #
#434000000
b0000000011011001 !
b0000000011011001 #
#436000000
b0000000011011010 !
b0000000011011010 #
#438000000
b0000000011011011 !
b0000000011011011 #
#440000000
b0000000011011100 !
b0000000011011100 #
#442000000
b0000000011011101 !
b0000000011011101 #
#444000000
b0000000011011110 !
b0000000011011110 #
#446000000
b0000000011011111 !
b0000000011011111 #
#448000000
b0000000011100000 !
b0000000011100000 #
#450000000
b0000000011100001 !
b0000000011100001 #
#452000000
b0000000011100010 !
b0000000011100010 #
#454000000
b0000000011100011 !
b0000000011100011 #
#456000000
b0000000011100100 !
b0000000011100100 #
#458000000
b0000000011100101 !
b0000000011100101 #
#460000000
b0000000011100110 !
b0000000011100110 #
#462000000
b0000000011100111 !
b0000000011100111 #
#464000000
b0000000011101000 !
b0000000011101000 #
#466000000
b0000000011101001 !
b0000000011101001 #
#468000000
b0000000011101010 !
b0000000011101010 #
#470000000
b0000000011101011 !
b0000000011101011 #
#472000000
b0000000011101100 !
b0000000011101100 #
#474000000
b0000000011101101 !
b0000000011101101 #
#476000000
b0000000011101110 !
b0000000011101110 #
#478000000
b0000000011101111 !
b0000000011101111 #
#480000000
b0000000011110000 !
b0000000011110000 #
#482000000
b0000000011110001 !
b0000000011110001 #
#484000000
b0000000011110010 !
b0000000011110010 #
#486000000
b0000000011110011 !
b0000000011110011 #
#488000000
b0000000011110100 !
b0000000011110100 #
#490000000
b0000000011110101 !
b0000000011110101 #
#492000000
b0000000011110110 !
b0000000011110110 #
#494000000
b0000000011110111 !
b0000000011110111 #
#496000000
b0000000011111000 !
b0000000011111000 #
#498000000
b0000000011111001 !
b0000000011111001 #
#500000000
b0000000011111010 !
b0000000011111010 #
#502000000
b0000000011111011 !
b0000000011111011 #
#504000000
b0000000011111100 !
b0000000011111100 #
#506000000
b0000000011111101 !
b0000000011111101 #
#508000000
b0000000011111110 !
b0000000011111110 #
#510000000
b0000000011111111 !
b0000000011111111 #
#512000000
b0000000100000000 !
b1000 "
b0000000100000000 #
b1000 $
#514000000
b0000000100000001 !
b0000000100000001 #
#516000000
b0000000100000010 !
b0000000100000010 #
#518000000
b0000000100000011 !
b0000000100000011 #
#520000000
b0000000100000100 !
b0000000100000100 #
#522000000
b0000000100000101 !
b0000000100000101 #
#524000000
b0000000100000110 !
b0000000100000110 #
#526000000
b0000000100000111 !
b0000000100000111 #
#528000000
b0000000100001000 !
b0000000100001000 #
#530000000
b0000000100001001 !
b0000000100001001 #
#532000000
b0000000100001010 !
b0000000100001010 #
#534000000
b0000000100001011 !
b0000000100001011 #
#536000000
b0000000100001100 !
b0000000100001100 #
#538000000
b0000000100001101 !
b0000000100001101 #
#540000000
b0000000100001110 !
b0000000100001110 #
#542000000
b0000000100001111 !
b0000000100001111 #
#544000000
b0000000100010000 !
b0000000100010000 #
#546000000
b0000000100010001 !
b0000000100010001 #
#548000000
b0000000100010010 !
b0000000100010010 #
#550000000
b0000000100010011 !
b0000000100010011 #
#552000000
b0000000100010100 !
b0000000100010100 #
#554000000
b0000000100010101 !
b0000000100010101 #
#556000000
b0000000100010110 !
b0000000100010110 #
#558000000
b0000000100010111 !
b0000000100010111 #
#560000000
b0000000100011000 !
b0000000100011000 #
#562000000
b0000000100011001 !
b0000000100011001 #
#564000000
b0000000100011010 !
b0000000100011010 #
#566000000
b0000000100011011 !
b0000000100011011 #
#568000000
b0000000100011100 !
b0000000100011100 #
#570000000
b0000000100011101 !
b0000000100011101 #
#572000000
b0000000100011110 !
b0000000100011110 #
#574000000
b0000000100011111 !
b0000000100011111 #
#576000000
b0000000100100000 !
b0000000100100000 #
#578000000
b0000000100100001 !
b0000000100100001 #
#580000000
b0000000100100010 !
b0000000100100010 #
#582000000
b0000000100100011 !
b0000000100100011 #
#584000000
b0000000100100100 !
b0000000100100100 #
#586000000
b0000000100100101 !
b0000000100100101 #
#588000000
b0000000100100110 !
b0000000100100110 #
#590000000
b0000000100100111 !
b0000000100100111 #
#592000000
b0000000100101000 !
b0000000100101000 #
#594000000
b0000000100101001 !
b0000000100101001 #
#596000000
b0000000100101010 !
b0000000100101010 #
#598000000
b0000000100101011 !
b0000000100101011 #
#600000000
b0000000100101100 !
b0000000100101100 #
#602000000
b0000000100101101 !
b0000000100101101 #
#604000000
b0000000100101110 !
b0000000100101110 #
#606000000
b0000000100101111 !
b0000000100101111 #
#608000000
b0000000100110000 !
b0000000100110000 #
#610000000
b0000000100110001 !
b0000000100110001 #
#612000000
b0000000100110010 !
b0000000100110010 #
#614000000
b0000000100110011 !
b0000000100110011 #
#616000000
b0000000100110100 !
b0000000100110100 #
#618000000
b0000000100110101 !
b0000000100110101 #
#620000000
b0000000100110110 !
b0000000100110110 #
#622000000
b0000000100110111 !
b0000000100110111 #
#624000000
b0000000100111000 !
b0000000100111000 #
#626000000
b0000000100111001 !
b0000000100111001 #
#628000000
b0000000100111010 !
b0000000100111010 #
#630000000
b0000000100111011 !
b0000000100111011 #
#632000000
b0000000100111100 !
b0000000100111100 #
#634000000
b0000000100111101 !
b0000000100111101 #
#636000000
b0000000100111110 !
b0000000100111110 #
#638000000
b0000000100111111 !
b0000000100111111 #
#640000000
b0000000101000000 !
b0000000101000000 #
#642000000
b0000000101000001 !
b0000000101000001 #
#644000000
b0000000101000010 !
b0000000101000010 #
#646000000
b0000000101000011 !
b0000000101000011 #
#648000000
b0000000101000100 !
b0000000101000100 #
#650000000
b0000000101000101 !
b0000000101000101 #
#652000000
b0000000101000110 !
b0000000101000110 #
#654000000
b0000000101000111 !
b0000000101000111 #
#656000000
b0000000101001000 !
b0000000101001000 #
#658000000
b0000000101001001 !
b0000000101001001 #
#660000000
b0000000101001010 !
b0000000101001010 #
#662000000
b0000000101001011 !
b0000000101001011 #
#664000000
b0000000101001100 !
b0000000101001100 #
#666000000
b0000000101001101 !
b0000000101001101 #
#668000000
b0000000101001110 !
b0000000101001110 #
#670000000
b0000000101001111 !
b0000000101001111 #
#672000000
b0000000101010000 !
b0000000101010000 #
#674000000
b0000000101010001 !
b0000000101010001 #
#676000000
b0000000101010010 !
b0000000101010010 #
#678000000
b0000000101010011 !
b0000000101010011 #
#680000000
b0000000101010100 !
b0000000101010100 #
#682000000
b0000000101010101 !
b0000000101010101 #
#684000000
b0000000101010110 !
b0000000101010110 #
#686000000
b0000000101010111 !
b0000000101010111 #
#688000000
b0000000101011000 !
b0000000101011000 #
#690000000
b0000000101011001 !
b0000000101011001 #
#692000000
b0000000101011010 !
b0000000101011010 #
#694000000
b0000000101011011 !
b0000000101011011 #
#696000000
b0000000101011100 !
b0000000101011100 #
#698000000
b0000000101011101 !
b0000000101011101 #
#700000000
b0000000101011110 !
b0000000101011110 #
#702000000
b0000000101011111 !
b0000000101011111 #
#704000000
b0000000101100000 !
b0000000101100000 #
#706000000
b0000000101100001 !
b0000000101100001 #
#708000000
b0000000101100010 !
b0000000101100010 #
#710000000
b0000000101100011 !
b0000000101100011 #
#712000000
b0000000101100100 !
b0000000101100100 #
#714000000
b0000000101100101 !
b0000000101100101 #
#716000000
b0000000101100110 !
b0000000101100110 #
#718000000
b0000000101100111 !
b0000000101100111 #
#720000000
b0000000101101000 !
b0000000101101000 #
#722000000
b0000000101101001 !
b0000000101101001 #
#724000000
b0000000101101010 !
b0000000101101010 #
#726000000
b0000000101101011 !
b0000000101101011 #
#728000000
b0000000101101100 !
b0000000101101100 #
#730000000
b0000000101101101 !
b0000000101101101 #
#732000000
b0000000101101110 !
b0000000101101110 #
#734000000
b0000000101101111 !
b0000000101101111 #
#736000000
b0000000101110000 !
b0000000101110000 #
#738000000
b0000000101110001 !
b0000000101110001 #
#740000000
b0000000101110010 !
b0000000101110010 #
#742000000
b0000000101110011 !
b0000000101110011 #
#744000000
b0000000101110100 !
b0000000101110100 #
#746000000
b0000000101110101 !
b0000000101110101 #
#748000000
b0000000101110110 !
b0000000101110110 #
#750000000
b0000000101110111 !
b0000000101110111 #
#752000000
b0000000101111000 !
b0000000101111000 #
#754000000
b0000000101111001 !
b0000000101111001 #
#756000000
b0000000101111010 !
b0000000101111010 #
#758000000
b0000000101111011 !
b0000000101111011 #
#760000000
b0000000101111100 !
b0000000101111100 #
#762000000
b0000000101111101 !
b0000000101111101 #
#764000000
b0000000101111110 !
b0000000101111110 #
#766000000
b0000000101111111 !
b0000000101111111 #
#768000000
b0000000110000000 !
b0000000110000000 #
#770000000
b0000000110000001 !
b0000000110000001 #
#772000000
b0000000110000010 !
b0000000110000010 #
#774000000
b0000000110000011 !
b0000000110000011 #
#776000000
b0000000110000100 !
b0000000110000100 #
#778000000
b0000000110000101 !
b0000000110000101 #
#780000000
b0000000110000110 !
b0000000110000110 #
#782000000
b0000000110000111 !
b0000000110000111 #
#784000000
b0000000110001000 !
b0000000110001000 #
#786000000
b0000000110001001 !
b0000000110001001 #
#788000000
b0000000110001010 !
b0000000110001010 #
#790000000
b0000000110001011 !
b0000000110001011 #
#792000000
b0000000110001100 !
b0000000110001100 #
#794000000
b0000000110001101 !
b0000000110001101 #
#796000000
b0000000110001110 !
b0000000110001110 #
#798000000
b0000000110001111 !
b0000000110001111 #
#800000000
b0000000110010000 !
b0000000110010000 #
#802000000
b0000000110010001 !
b0000000110010001 #
#804000000
b0000000110010010 !
b0000000110010010 #
#806000000
b0000000110010011 !
b0000000110010011 #
#808000000
b0000000110010100 !
b0000000110010100 #
#810000000
b0000000110010101 !
b0000000110010101 #
#812000000
b0000000110010110 !
b0000000110010110 #
#814000000
b0000000110010111 !
b0000000110010111 #
#816000000
b0000000110011000 !
b0000000110011000 #
#818000000
b0000000110011001 !
b0000000110011001 #
#820000000
b0000000110011010 !
b0000000110011010 #
#822000000
b0000000110011011 !
b0000000110011011 #
#824000000
b0000000110011100 !
b0000000110011100 #
#826000000
b0000000110011101 !
b0000000110011101 #
#828000000
b0000000110011110 !
b0000000110011110 #
#830000000
b0000000110011111 !
b0000000110011111 #
#832000000
b0000000110100000 !
b0000000110100000 #
#834000000
b0000000110100001 !
b0000000110100001 #
#836000000
b0000000110100010 !
b0000000110100010 #
#838000000
b0000000110100011 !
b0000000110100011 #
#840000000
b0000000110100100 !
b0000000110100100 #
#842000000
b0000000110100101 !
b0000000110100101 #
#844000000
b0000000110100110 !
b0000000110100110 #
#846000000
b0000000110100111 !
b0000000110100111 #
#848000000
b0000000110101000 !
b0000000110101000 #
#850000000
b0000000110101001 !
b0000000110101001 #
#852000000
b0000000110101010 !
b0000000110101010 #
#854000000
b0000000110101011 !
b0000000110101011 #
#856000000
b0000000110101100 !
b0000000110101100 #
#858000000
b0000000110101101 !
b0000000110101101 #
#860000000
b0000000110101110 !
b0000000110101110 #
#862000000
b0000000110101111 !
b0000000110101111 #
#864000000
b0000000110110000 !
b0000000110110000 #
#866000000
b0000000110110001 !
b0000000110110001 #
#868000000
b0000000110110010 !
b0000000110110010 #
#870000000
b0000000110110011 !
b0000000110110011 #
#872000000
b0000000110110100 !
b0000000110110100 #
#874000000
b0000000110110101 !
b0000000110110101 #
#876000000
b0000000110110110 !
b0000000110110110 #
#878000000
b0000000110110111 !
b0000000110110111 #
#880000000
b0000000110111000 !
b0000000110111000 #
#882000000
b0000000110111001 !
b0000000110111001 #
#884000000
b0000000110111010 !
b0000000110111010 #
#886000000
b0000000110111011 !
b0000000110111011 #
#888000000
b0000000110111100 !
b0000000110111100 #
#890000000
b0000000110111101 !
b0000000110111101 #
#892000000
b0000000110111110 !
b0000000110111110 #
#894000000
b0000000110111111 !
b0000000110111111 #
#896000000
b0000000111000000 !
b0000000111000000 #
#898000000
b0000000111000001 !
b0000000111000001 #
#900000000
b0000000111000010 !
b0000000111000010 #
#902000000
b0000000111000011 !
b0000000111000011 #
#904000000
b0000000111000100 !
b0000000111000100 #
#906000000
b0000000111000101 !
b0000000111000101 #
#908000000
b0000000111000110 !
b0000000111000110 #
#910000000
b0000000111000111 !
b0000000111000111 #
#912000000
b0000000111001000 !
b0000000111001000 #
#914000000
b0000000111001001 !
b0000000111001001 #
#916000000
b0000000111001010 !
b0000000111001010 #
#918000000
b0000000111001011 !
b0000000111001011 #
#920000000
b0000000111001100 !
b0000000111001100 #
#922000000
b0000000111001101 !
b0000000111001101 #
#924000000
b0000000111001110 !
b0000000111001110 #
#926000000
b0000000111001111 !
b0000000111001111 #
#928000000
b0000000111010000 !
b0000000111010000 #
#930000000
b0000000111010001 !
b0000000111010001 #
#932000000
b0000000111010010 !
b0000000111010010 #
#934000000
b0000000111010011 !
b0000000111010011 #
#936000000
b0000000111010100 !
b0000000111010100 #
#938000000
b0000000111010101 !
b0000000111010101 #
#940000000
b0000000111010110 !
b0000000111010110 #
#942000000
b0000000111010111 !
b0000000111010111 #
#944000000
b0000000111011000 !
b0000000111011000 #
#946000000
b0000000111011001 !
b0000000111011001 #
#948000000
b0000000111011010 !
b0000000111011010 #
#950000000
b0000000111011011 !
b0000000111011011 #
#952000000
b0000000111011100 !
b0000000111011100 #
#954000000
b0000000111011101 !
b0000000111011101 #
#956000000
b0000000111011110 !
b0000000111011110 #
#958000000
b0000000111011111 !
b0000000111011111 #
#960000000
b0000000111100000 !
b0000000111100000 #
#962000000
b0000000111100001 !
b0000000111100001 #
#964000000
b0000000111100010 !
b0000000111100010 #
#966000000
b0000000111100011 !
b0000000111100011 #
#968000000
b0000000111100100 !
b0000000111100100 #
#970000000
b0000000111100101 !
b0000000111100101 #
#972000000
b0000000111100110 !
b0000000111100110 #
#974000000
b0000000111100111 !
b0000000111100111 #
#976000000
b0000000111101000 !
b0000000111101000 #
#978000000
b0000000111101001 !
b0000000111101001 #
#980000000
b0000000111101010 !
b0000000111101010 #
#982000000
b0000000111101011 !
b0000000111101011 #
#984000000
b0000000111101100 !
b0000000111101100 #
#986000000
b0000000111101101 !
b0000000111101101 #
#988000000
b0000000111101110 !
b0000000111101110 #
#990000000
b0000000111101111 !
b0000000111101111 #
#992000000
b0000000111110000 !
b0000000111110000 #
#994000000
b0000000111110001 !
b0000000111110001 #
#996000000
b0000000111110010 !
b0000000111110010 #
#998000000
b0000000111110011 !
b0000000111110011 #
#1000000000
b0000000111110100 !
b0000000111110100 #
#1002000000
b0000000111110101 !
b0000000111110101 #
#1004000000
b0000000111110110 !
b0000000111110110 #
#1006000000
b0000000111110111 !
b0000000111110111 #
#1008000000
b0000000111111000 !
b0000000111111000 #
#1010000000
b0000000111111001 !
b0000000111111001 #
#1012000000
b0000000111111010 !
b0000000111111010 #
#1014000000
b0000000111111011 !
b0000000111111011 #
#1016000000
b0000000111111100 !
b0000000111111100 #
#1018000000
b0000000111111101 !
b0000000111111101 #
#1020000000
b0000000111111110 !
b0000000111111110 #
#1022000000
b0000000111111111 !
b0000000111111111 #
#1024000000
b0000001000000000 !
b1001 "
b0000001000000000 #
b1001 $
#1026000000
b0000001000000001 !
b0000001000000001 #
#1028000000
b0000001000000010 !
b0000001000000010 #
#1030000000
b0000001000000011 !
b0000001000000011 #
#1032000000
b0000001000000100 !
b0000001000000100 #
#1034000000
b0000001000000101 !
b0000001000000101 #
#1036000000
b0000001000000110 !
b0000001000000110 #
#1038000000
b0000001000000111 !
b0000001000000111 #
#1040000000
b0000001000001000 !
b0000001000001000 #
#1042000000
b0000001000001001 !
b0000001000001001 #
#1044000000
b0000001000001010 !
b0000001000001010 #
#1046000000
b0000001000001011 !
b0000001000001011 #
#1048000000
b0000001000001100 !
b0000001000001100 #
#1050000000
b0000001000001101 !
b0000001000001101 #
#1052000000
b0000001000001110 !
b0000001000001110 #
#1054000000
b0000001000001111 !
b0000001000001111 #
#1056000000
b0000001000010000 !
b0000001000010000 #
#1058000000
b0000001000010001 !
b0000001000010001 #
#1060000000
b0000001000010010 !
b0000001000010010 #
#1062000000
b0000001000010011 !
b0000001000010011 #
#1064000000
b0000001000010100 !
b0000001000010100 #
#1066000000
b0000001000010101 !
b0000001000010101 #
#1068000000
b0000001000010110 !
b0000001000010110 #
#1070000000
b0000001000010111 !
b0000001000010111 #
