encoder/enc8x3_sel.vhd
LIBRARY ieee;
USE IEEE.STD_LOGIC_1164.ALL;
USE IEEE.STD_LOGIC_ARITH.ALL;
USE IEEE.STD_LOGIC_UNSIGNED.ALL;

ENTITY enc8x3_sel IS
    PORT (
        x : IN STD_LOGIC_VECTOR(7 DOWNTO 0);
        y : OUT STD_LOGIC_VECTOR(2 DOWNTO 0));

END enc8x3_sel;

ARCHITECTURE rtl OF enc8x3_sel IS

BEGIN
    WITH x SELECT
        y <= TRANSPORT "000" AFTER 10 ns WHEN "00000001",
        "001" AFTER 10 ns WHEN "00000010",
        "010" WHEN "00000100",
        "011" WHEN "00001000",
        "100" WHEN "00010000",
        "101" WHEN "00100000",
        "110" WHEN "01000000",
        "111" WHEN "10000000",
        "000" WHEN OTHERS;
END ARCHITECTURE;

encoder/enc8x3_sel_test.vhd
LIBRARY IEEE;
USE IEEE.STD_LOGIC_1164.ALL;
USE IEEE.STD_LOGIC_ARITH.ALL;
USE IEEE.STD_LOGIC_UNSIGNED.ALL;
USE IEEE.NUMERIC_STD.ALL;

--this is how entity for your test bench code has to be declared.
ENTITY enc8x3_sel_test IS
END enc8x3_sel_test;

ARCHITECTURE behavior OF enc8x3_sel_test IS
    --signal declarations.
    SIGNAL x : STD_LOGIC_VECTOR(7 DOWNTO 0) := (OTHERS => '0');
    SIGNAL y : STD_LOGIC_VECTOR(2 DOWNTO 0) := (OTHERS => '0');

BEGIN
    --entity instantiation
    UUT : ENTITY work.enc8x3_sel PORT MAP(x, y);

    --definition of simulation process
    tb : PROCESS
    BEGIN

        x <= "00000000";
        WAIT FOR 100 ns;

        x <= "00000010";
        WAIT FOR 100 ns;

        x <= "00000000";
        WAIT FOR 20 ns;

        x <= "00000010";
        WAIT FOR 80 ns;

        x <= "00000100";
        WAIT FOR 100 ns;

        x <= "00000000";
        WAIT FOR 20 ns;

        x <= "00000100";
        WAIT FOR 80 ns;

        x <= "00000000";

        WAIT FOR 100 ns;
        
    END PROCESS tb;
END;

waves/enc8x3_sel_test.vcd
$date
  Mon Apr 11 23:00:59 2022
$end
$version
  GHDL v0
$end
$timescale
  1 fs
$end
$scope module standard $end
$upscope $end
$scope module textio $end
$upscope $end
$scope module std_logic_1164 $end
$upscope $end
$scope module std_logic_arith $end
$upscope $end
$scope module std_logic_unsigned $end
$upscope $end
$scope module numeric_std $end
$upscope $end
$scope module enc8x3_sel_test $end
$var reg 8 ! x[7:0] $end
$var reg 3 " y[2:0] $end
$scope module uut $end
$var reg 8 # x[7:0] $end
$var reg 3 $ y[2:0] $end
$upscope $end
$upscope $end
$enddefinitions $end
#0
b00000000 !
b000 "
b00000000 #
b000 $
#100000000
b00000010 !
b00000010 #
#110000000
b001 "
b001 $
#200000000
b00000000 !
b000 "
b00000000 #
b000 $
#220000000
b00000010 !
b00000010 #
#230000000
b001 "
b001 $
#300000000
b00000100 !
b010 "
b00000100 #
b010 $
#400000000
b00000000 !
b000 "
b00000000 #
b000 $
#420000000
b00000100 !
b010 "
b00000100 #
b010 $
#500000000
b00000000 !
b000 "
b00000000 #
b000 $
#600000000
#700000000
b00000010 !
b00000010 #
#710000000
b001 "
b001 $
#800000000
b00000000 !
b000 "
b00000000 #
b000 $
#820000000
b00000010 !
b00000010 #
#830000000
b001 "
b001 $
#900000000
b00000100 !
b010 "
b00000100 #
b010 $
#1000000000
b00000000 !
b000 "
b00000000 #
b000 $
