mux/mux8x1_sel.vhd
LIBRARY IEEE;
USE IEEE.STD_LOGIC_1164.ALL;
USE IEEE.STD_LOGIC_ARITH.ALL;
USE IEEE.STD_LOGIC_UNSIGNED.ALL;

ENTITY mux8x1_sel IS
    PORT (
        sel : IN STD_LOGIC_VECTOR(2 DOWNTO 0);
        x : IN STD_LOGIC_VECTOR(7 DOWNTO 0);
        y : OUT STD_LOGIC
    );

END mux8x1_sel;

ARCHITECTURE behavioral OF mux8x1_sel IS
BEGIN
    WITH sel SELECT
        y <= TRANSPORT x(0) AFTER 50 ns WHEN "000",
        x(1) AFTER 50 ns WHEN "001",
        x(2) WHEN "010",
        x(3) WHEN "011",
        x(4) WHEN "100",
        x(5) WHEN "101",
        x(6) WHEN "110",
        x(7) WHEN "111",
        'X' WHEN OTHERS;

END ARCHITECTURE;

mux/mux8x1_sel_test.vhd
LIBRARY IEEE;
USE IEEE.STD_LOGIC_1164.ALL;
USE IEEE.STD_LOGIC_ARITH.ALL;
USE IEEE.STD_LOGIC_UNSIGNED.ALL;
USE IEEE.NUMERIC_STD.ALL;

--this is how entity for your test bench code has to be declared.
ENTITY mux8x1_sel_test IS
END mux8x1_sel_test;

ARCHITECTURE behavior OF mux8x1_sel_test IS
    --signal declarations.
    SIGNAL x : STD_LOGIC_VECTOR(7 DOWNTO 0) := (OTHERS => '0');
    SIGNAL sel : STD_LOGIC_VECTOR(2 DOWNTO 0) := (OTHERS => '0');
    SIGNAL y : STD_LOGIC;
BEGIN
    --entity instantiation
    UUT : ENTITY work.mux8x1_sel PORT MAP(sel, x, y);

    --definition of simulation process
    tb : PROCESS
    BEGIN
        -- Transport delay
        sel <= "000";

        x <= "00000001";
        WAIT FOR 60 ns;

        x <= "00000000";
        WAIT FOR 500 ps;

        x <= "00000001";
        WAIT FOR 30 ns;

        x <= "00000000";
        WAIT FOR 100 ns;

        -- Inertial delay
        sel <= "001";

        x <= "00000010";
        WAIT FOR 60 ns;

        x <= "00000000";
        WAIT FOR 500 ps;

        x <= "00000010";
        WAIT FOR 30 ns;


        -- Done
        x <= "00000000";
        WAIT FOR 100 ns;

    END PROCESS tb;
END;

waves/mux8x1_sel_test.vcd
$date
  Mon Apr 11 21:34:42 2022
$end
$version
  GHDL v0
$end
$timescale
  1 fs
$end
$scope module standard $end
$upscope $end
$scope module textio $end
$upscope $end
$scope module std_logic_1164 $end
$upscope $end
$scope module std_logic_arith $end
$upscope $end
$scope module std_logic_unsigned $end
$upscope $end
$scope module numeric_std $end
$upscope $end
$scope module mux8x1_sel_test $end
$var reg 8 ! x[7:0] $end
$var reg 3 " sel[2:0] $end
$var reg 1 # y $end
$scope module uut $end
$var reg 3 $ sel[2:0] $end
$var reg 8 % x[7:0] $end
$var reg 1 & y $end
$upscope $end
$upscope $end
$enddefinitions $end
#0
b00000001 !
b000 "
U#
b000 $
b00000001 %
U&
#50000000
1#
1&
#60000000
b00000000 !
b00000000 %
#60500000
b00000001 !
b00000001 %
#90500000
b00000000 !
b00000000 %
#110000000
0#
0&
#110500000
1#
1&
#140500000
0#
0&
#190500000
b00000010 !
b001 "
b001 $
b00000010 %
#240500000
1#
1&
#250500000
b00000000 !
b00000000 %
#251000000
b00000010 !
b00000010 %
#281000000
b00000000 !
b00000000 %
#300500000
0#
0&
#301000000
1#
1&
#331000000
0#
0&
#381000000
b00000001 !
b000 "
b000 $
b00000001 %
