mux/mux8x1_concurrent.vhd
LIBRARY IEEE;
USE IEEE.STD_LOGIC_1164.ALL;
USE IEEE.STD_LOGIC_ARITH.ALL;
USE IEEE.STD_LOGIC_UNSIGNED.ALL;

ENTITY mux8x1_concurrent IS
    PORT (
        sel : IN STD_LOGIC_VECTOR(2 DOWNTO 0);
        x : IN STD_LOGIC_VECTOR(7 DOWNTO 0);
        y : OUT STD_LOGIC
    );

END mux8x1_concurrent;

ARCHITECTURE behavioral OF mux8x1_concurrent IS
BEGIN
    y <=
        (x(0) AND (NOT sel(0)) AND (NOT sel(1)) AND (NOT sel(2))) OR
        (x(1) AND (NOT sel(0)) AND (NOT sel(1)) AND sel(2)) OR
        (x(2) AND (NOT sel(0)) AND sel(1) AND (NOT sel(2))) OR
        (x(3) AND (NOT sel(0)) AND sel(1) AND sel(2)) OR
        (x(4) AND sel(0) AND (NOT sel(1)) AND (NOT sel(2))) OR
        (x(5) AND sel(0) AND (NOT sel(1)) AND sel(2)) OR
        (x(6) AND sel(0) AND sel(1) AND (NOT sel(2))) OR
        (x(7) AND sel(0) AND sel(1) AND sel(2));

END ARCHITECTURE;

mux/mux8x1_concurrent_test.vhd
LIBRARY IEEE;
USE IEEE.STD_LOGIC_1164.ALL;
USE IEEE.STD_LOGIC_ARITH.ALL;
USE IEEE.STD_LOGIC_UNSIGNED.ALL;
use IEEE.NUMERIC_STD.ALL;

--this is how entity for your test bench code has to be declared.
ENTITY mux8x1_concurrent_test IS
END mux8x1_concurrent_test;

ARCHITECTURE behavior OF mux8x1_concurrent_test IS
    --signal declarations.
    SIGNAL x : STD_LOGIC_VECTOR(7 DOWNTO 0) := (OTHERS => '0');
    SIGNAL sel : STD_LOGIC_VECTOR(2 DOWNTO 0) := (OTHERS => '0');
    SIGNAL y : STD_LOGIC;

BEGIN
    --entity instantiation
    UUT : ENTITY work.mux8x1_concurrent PORT MAP(sel, x, y);

    --definition of simulation process
    tb : PROCESS
    BEGIN
        FOR i IN 0 TO 2 ** sel'length - 1 LOOP
            FOR j IN 0 TO 2 ** x'length - 1 LOOP
                sel <= STD_LOGIC_VECTOR(to_unsigned(i, sel'length));
                x <= STD_LOGIC_VECTOR(to_unsigned(j, x'length));
                WAIT FOR 2 ns;
            END LOOP;
        END LOOP;
    END PROCESS tb;
END;

waves/mux8x1_concurrent_test.vcd
$date
  Sun Mar 13 00:04:55 2022
$end
$version
  GHDL v0
$end
$timescale
  1 fs
$end
$scope module standard $end
$upscope $end
$scope module textio $end
$upscope $end
$scope module std_logic_1164 $end
$upscope $end
$scope module std_logic_arith $end
$upscope $end
$scope module std_logic_unsigned $end
$upscope $end
$scope module numeric_std $end
$upscope $end
$scope module mux8x1_concurrent_test $end
$var reg 8 ! x[7:0] $end
$var reg 3 " sel[2:0] $end
$var reg 1 # y $end
$scope module uut $end
$var reg 3 $ sel[2:0] $end
$var reg 8 % x[7:0] $end
$var reg 1 & y $end
$upscope $end
$upscope $end
$enddefinitions $end
#0
b00000000 !
b000 "
0#
b000 $
b00000000 %
0&
#2000000
b00000001 !
1#
b00000001 %
1&
#4000000
b00000010 !
0#
b00000010 %
0&
#6000000
b00000011 !
1#
b00000011 %
1&
#8000000
b00000100 !
0#
b00000100 %
0&
#10000000
b00000101 !
1#
b00000101 %
1&
#12000000
b00000110 !
0#
b00000110 %
0&
#14000000
b00000111 !
1#
b00000111 %
1&
#16000000
b00001000 !
0#
b00001000 %
0&
#18000000
b00001001 !
1#
b00001001 %
1&
#20000000
b00001010 !
0#
b00001010 %
0&
#22000000
b00001011 !
1#
b00001011 %
1&
#24000000
b00001100 !
0#
b00001100 %
0&
#26000000
b00001101 !
1#
b00001101 %
1&
#28000000
b00001110 !
0#
b00001110 %
0&
#30000000
b00001111 !
1#
b00001111 %
1&
#32000000
b00010000 !
0#
b00010000 %
0&
#34000000
b00010001 !
1#
b00010001 %
1&
#36000000
b00010010 !
0#
b00010010 %
0&
#38000000
b00010011 !
1#
b00010011 %
1&
#40000000
b00010100 !
0#
b00010100 %
0&
#42000000
b00010101 !
1#
b00010101 %
1&
#44000000
b00010110 !
0#
b00010110 %
0&
#46000000
b00010111 !
1#
b00010111 %
1&
#48000000
b00011000 !
0#
b00011000 %
0&
#50000000
b00011001 !
1#
b00011001 %
1&
#52000000
b00011010 !
0#
b00011010 %
0&
#54000000
b00011011 !
1#
b00011011 %
1&
#56000000
b00011100 !
0#
b00011100 %
0&
#58000000
b00011101 !
1#
b00011101 %
1&
#60000000
b00011110 !
0#
b00011110 %
0&
#62000000
b00011111 !
1#
b00011111 %
1&
#64000000
b00100000 !
0#
b00100000 %
0&
#66000000
b00100001 !
1#
b00100001 %
1&
#68000000
b00100010 !
0#
b00100010 %
0&
#70000000
b00100011 !
1#
b00100011 %
1&
#72000000
b00100100 !
0#
b00100100 %
0&
#74000000
b00100101 !
1#
b00100101 %
1&
#76000000
b00100110 !
0#
b00100110 %
0&
#78000000
b00100111 !
1#
b00100111 %
1&
#80000000
b00101000 !
0#
b00101000 %
0&
#82000000
b00101001 !
1#
b00101001 %
1&
#84000000
b00101010 !
0#
b00101010 %
0&
#86000000
b00101011 !
1#
b00101011 %
1&
#88000000
b00101100 !
0#
b00101100 %
0&
#90000000
b00101101 !
1#
b00101101 %
1&
#92000000
b00101110 !
0#
b00101110 %
0&
#94000000
b00101111 !
1#
b00101111 %
1&
#96000000
b00110000 !
0#
b00110000 %
0&
#98000000
b00110001 !
1#
b00110001 %
1&
#100000000
b00110010 !
0#
b00110010 %
0&
#102000000
b00110011 !
1#
b00110011 %
1&
#104000000
b00110100 !
0#
b00110100 %
0&
#106000000
b00110101 !
1#
b00110101 %
1&
#108000000
b00110110 !
0#
b00110110 %
0&
#110000000
b00110111 !
1#
b00110111 %
1&
#112000000
b00111000 !
0#
b00111000 %
0&
#114000000
b00111001 !
1#
b00111001 %
1&
#116000000
b00111010 !
0#
b00111010 %
0&
#118000000
b00111011 !
1#
b00111011 %
1&
#120000000
b00111100 !
0#
b00111100 %
0&
#122000000
b00111101 !
1#
b00111101 %
1&
#124000000
b00111110 !
0#
b00111110 %
0&
#126000000
b00111111 !
1#
b00111111 %
1&
#128000000
b01000000 !
0#
b01000000 %
0&
#130000000
b01000001 !
1#
b01000001 %
1&
#132000000
b01000010 !
0#
b01000010 %
0&
#134000000
b01000011 !
1#
b01000011 %
1&
#136000000
b01000100 !
0#
b01000100 %
0&
#138000000
b01000101 !
1#
b01000101 %
1&
#140000000
b01000110 !
0#
b01000110 %
0&
#142000000
b01000111 !
1#
b01000111 %
1&
#144000000
b01001000 !
0#
b01001000 %
0&
#146000000
b01001001 !
1#
b01001001 %
1&
#148000000
b01001010 !
0#
b01001010 %
0&
#150000000
b01001011 !
1#
b01001011 %
1&
#152000000
b01001100 !
0#
b01001100 %
0&
#154000000
b01001101 !
1#
b01001101 %
1&
#156000000
b01001110 !
0#
b01001110 %
0&
#158000000
b01001111 !
1#
b01001111 %
1&
#160000000
b01010000 !
0#
b01010000 %
0&
#162000000
b01010001 !
1#
b01010001 %
1&
#164000000
b01010010 !
0#
b01010010 %
0&
#166000000
b01010011 !
1#
b01010011 %
1&
#168000000
b01010100 !
0#
b01010100 %
0&
#170000000
b01010101 !
1#
b01010101 %
1&
#172000000
b01010110 !
0#
b01010110 %
0&
#174000000
b01010111 !
1#
b01010111 %
1&
#176000000
b01011000 !
0#
b01011000 %
0&
#178000000
b01011001 !
1#
b01011001 %
1&
#180000000
b01011010 !
0#
b01011010 %
0&
#182000000
b01011011 !
1#
b01011011 %
1&
#184000000
b01011100 !
0#
b01011100 %
0&
#186000000
b01011101 !
1#
b01011101 %
1&
#188000000
b01011110 !
0#
b01011110 %
0&
#190000000
b01011111 !
1#
b01011111 %
1&
#192000000
b01100000 !
0#
b01100000 %
0&
#194000000
b01100001 !
1#
b01100001 %
1&
#196000000
b01100010 !
0#
b01100010 %
0&
#198000000
b01100011 !
1#
b01100011 %
1&
#200000000
b01100100 !
0#
b01100100 %
0&
#202000000
b01100101 !
1#
b01100101 %
1&
#204000000
b01100110 !
0#
b01100110 %
0&
#206000000
b01100111 !
1#
b01100111 %
1&
#208000000
b01101000 !
0#
b01101000 %
0&
#210000000
b01101001 !
1#
b01101001 %
1&
#212000000
b01101010 !
0#
b01101010 %
0&
#214000000
b01101011 !
1#
b01101011 %
1&
#216000000
b01101100 !
0#
b01101100 %
0&
#218000000
b01101101 !
1#
b01101101 %
1&
#220000000
b01101110 !
0#
b01101110 %
0&
#222000000
b01101111 !
1#
b01101111 %
1&
#224000000
b01110000 !
0#
b01110000 %
0&
#226000000
b01110001 !
1#
b01110001 %
1&
#228000000
b01110010 !
0#
b01110010 %
0&
#230000000
b01110011 !
1#
b01110011 %
1&
#232000000
b01110100 !
0#
b01110100 %
0&
#234000000
b01110101 !
1#
b01110101 %
1&
#236000000
b01110110 !
0#
b01110110 %
0&
#238000000
b01110111 !
1#
b01110111 %
1&
#240000000
b01111000 !
0#
b01111000 %
0&
#242000000
b01111001 !
1#
b01111001 %
1&
#244000000
b01111010 !
0#
b01111010 %
0&
#246000000
b01111011 !
1#
b01111011 %
1&
#248000000
b01111100 !
0#
b01111100 %
0&
#250000000
b01111101 !
1#
b01111101 %
1&
#252000000
b01111110 !
0#
b01111110 %
0&
#254000000
b01111111 !
1#
b01111111 %
1&
#256000000
b10000000 !
0#
b10000000 %
0&
#258000000
b10000001 !
1#
b10000001 %
1&
#260000000
b10000010 !
0#
b10000010 %
0&
#262000000
b10000011 !
1#
b10000011 %
1&
#264000000
b10000100 !
0#
b10000100 %
0&
#266000000
b10000101 !
1#
b10000101 %
1&
#268000000
b10000110 !
0#
b10000110 %
0&
#270000000
b10000111 !
1#
b10000111 %
1&
#272000000
b10001000 !
0#
b10001000 %
0&
#274000000
b10001001 !
1#
b10001001 %
1&
#276000000
b10001010 !
0#
b10001010 %
0&
#278000000
b10001011 !
1#
b10001011 %
1&
#280000000
b10001100 !
0#
b10001100 %
0&
#282000000
b10001101 !
1#
b10001101 %
1&
#284000000
b10001110 !
0#
b10001110 %
0&
#286000000
b10001111 !
1#
b10001111 %
1&
#288000000
b10010000 !
0#
b10010000 %
0&
#290000000
b10010001 !
1#
b10010001 %
1&
#292000000
b10010010 !
0#
b10010010 %
0&
#294000000
b10010011 !
1#
b10010011 %
1&
#296000000
b10010100 !
0#
b10010100 %
0&
#298000000
b10010101 !
1#
b10010101 %
1&
#300000000
b10010110 !
0#
b10010110 %
0&
#302000000
b10010111 !
1#
b10010111 %
1&
#304000000
b10011000 !
0#
b10011000 %
0&
#306000000
b10011001 !
1#
b10011001 %
1&
#308000000
b10011010 !
0#
b10011010 %
0&
#310000000
b10011011 !
1#
b10011011 %
1&
#312000000
b10011100 !
0#
b10011100 %
0&
#314000000
b10011101 !
1#
b10011101 %
1&
#316000000
b10011110 !
0#
b10011110 %
0&
#318000000
b10011111 !
1#
b10011111 %
1&
#320000000
b10100000 !
0#
b10100000 %
0&
#322000000
b10100001 !
1#
b10100001 %
1&
#324000000
b10100010 !
0#
b10100010 %
0&
#326000000
b10100011 !
1#
b10100011 %
1&
#328000000
b10100100 !
0#
b10100100 %
0&
#330000000
b10100101 !
1#
b10100101 %
1&
#332000000
b10100110 !
0#
b10100110 %
0&
#334000000
b10100111 !
1#
b10100111 %
1&
#336000000
b10101000 !
0#
b10101000 %
0&
#338000000
b10101001 !
1#
b10101001 %
1&
#340000000
b10101010 !
0#
b10101010 %
0&
#342000000
b10101011 !
1#
b10101011 %
1&
#344000000
b10101100 !
0#
b10101100 %
0&
#346000000
b10101101 !
1#
b10101101 %
1&
#348000000
b10101110 !
0#
b10101110 %
0&
#350000000
b10101111 !
1#
b10101111 %
1&
#352000000
b10110000 !
0#
b10110000 %
0&
#354000000
b10110001 !
1#
b10110001 %
1&
#356000000
b10110010 !
0#
b10110010 %
0&
#358000000
b10110011 !
1#
b10110011 %
1&
#360000000
b10110100 !
0#
b10110100 %
0&
#362000000
b10110101 !
1#
b10110101 %
1&
#364000000
b10110110 !
0#
b10110110 %
0&
#366000000
b10110111 !
1#
b10110111 %
1&
#368000000
b10111000 !
0#
b10111000 %
0&
#370000000
b10111001 !
1#
b10111001 %
1&
#372000000
b10111010 !
0#
b10111010 %
0&
#374000000
b10111011 !
1#
b10111011 %
1&
#376000000
b10111100 !
0#
b10111100 %
0&
#378000000
b10111101 !
1#
b10111101 %
1&
#380000000
b10111110 !
0#
b10111110 %
0&
#382000000
b10111111 !
1#
b10111111 %
1&
#384000000
b11000000 !
0#
b11000000 %
0&
#386000000
b11000001 !
1#
b11000001 %
1&
#388000000
b11000010 !
0#
b11000010 %
0&
#390000000
b11000011 !
1#
b11000011 %
1&
#392000000
b11000100 !
0#
b11000100 %
0&
#394000000
b11000101 !
1#
b11000101 %
1&
#396000000
b11000110 !
0#
b11000110 %
0&
#398000000
b11000111 !
1#
b11000111 %
1&
#400000000
b11001000 !
0#
b11001000 %
0&
#402000000
b11001001 !
1#
b11001001 %
1&
#404000000
b11001010 !
0#
b11001010 %
0&
#406000000
b11001011 !
1#
b11001011 %
1&
#408000000
b11001100 !
0#
b11001100 %
0&
#410000000
b11001101 !
1#
b11001101 %
1&
#412000000
b11001110 !
0#
b11001110 %
0&
#414000000
b11001111 !
1#
b11001111 %
1&
#416000000
b11010000 !
0#
b11010000 %
0&
#418000000
b11010001 !
1#
b11010001 %
1&
#420000000
b11010010 !
0#
b11010010 %
0&
#422000000
b11010011 !
1#
b11010011 %
1&
#424000000
b11010100 !
0#
b11010100 %
0&
#426000000
b11010101 !
1#
b11010101 %
1&
#428000000
b11010110 !
0#
b11010110 %
0&
#430000000
b11010111 !
1#
b11010111 %
1&
#432000000
b11011000 !
0#
b11011000 %
0&
#434000000
b11011001 !
1#
b11011001 %
1&
#436000000
b11011010 !
0#
b11011010 %
0&
#438000000
b11011011 !
1#
b11011011 %
1&
#440000000
b11011100 !
0#
b11011100 %
0&
#442000000
b11011101 !
1#
b11011101 %
1&
#444000000
b11011110 !
0#
b11011110 %
0&
#446000000
b11011111 !
1#
b11011111 %
1&
#448000000
b11100000 !
0#
b11100000 %
0&
#450000000
b11100001 !
1#
b11100001 %
1&
#452000000
b11100010 !
0#
b11100010 %
0&
#454000000
b11100011 !
1#
b11100011 %
1&
#456000000
b11100100 !
0#
b11100100 %
0&
#458000000
b11100101 !
1#
b11100101 %
1&
#460000000
b11100110 !
0#
b11100110 %
0&
#462000000
b11100111 !
1#
b11100111 %
1&
#464000000
b11101000 !
0#
b11101000 %
0&
#466000000
b11101001 !
1#
b11101001 %
1&
#468000000
b11101010 !
0#
b11101010 %
0&
#470000000
b11101011 !
1#
b11101011 %
1&
#472000000
b11101100 !
0#
b11101100 %
0&
#474000000
b11101101 !
1#
b11101101 %
1&
#476000000
b11101110 !
0#
b11101110 %
0&
#478000000
b11101111 !
1#
b11101111 %
1&
#480000000
b11110000 !
0#
b11110000 %
0&
#482000000
b11110001 !
1#
b11110001 %
1&
#484000000
b11110010 !
0#
b11110010 %
0&
#486000000
b11110011 !
1#
b11110011 %
1&
#488000000
b11110100 !
0#
b11110100 %
0&
#490000000
b11110101 !
1#
b11110101 %
1&
#492000000
b11110110 !
0#
b11110110 %
0&
#494000000
b11110111 !
1#
b11110111 %
1&
#496000000
b11111000 !
0#
b11111000 %
0&
#498000000
b11111001 !
1#
b11111001 %
1&
#500000000
b11111010 !
0#
b11111010 %
0&
#502000000
b11111011 !
1#
b11111011 %
1&
#504000000
b11111100 !
0#
b11111100 %
0&
#506000000
b11111101 !
1#
b11111101 %
1&
#508000000
b11111110 !
0#
b11111110 %
0&
#510000000
b11111111 !
1#
b11111111 %
1&
#512000000
b00000000 !
b001 "
0#
b001 $
b00000000 %
0&
#514000000
b00000001 !
b00000001 %
#516000000
b00000010 !
b00000010 %
#518000000
b00000011 !
b00000011 %
#520000000
b00000100 !
b00000100 %
#522000000
b00000101 !
b00000101 %
#524000000
b00000110 !
b00000110 %
#526000000
b00000111 !
b00000111 %
#528000000
b00001000 !
b00001000 %
#530000000
b00001001 !
b00001001 %
#532000000
b00001010 !
b00001010 %
#534000000
b00001011 !
b00001011 %
#536000000
b00001100 !
b00001100 %
#538000000
b00001101 !
b00001101 %
#540000000
b00001110 !
b00001110 %
#542000000
b00001111 !
b00001111 %
#544000000
b00010000 !
1#
b00010000 %
1&
#546000000
b00010001 !
b00010001 %
#548000000
b00010010 !
b00010010 %
#550000000
b00010011 !
b00010011 %
#552000000
b00010100 !
b00010100 %
#554000000
b00010101 !
b00010101 %
#556000000
b00010110 !
b00010110 %
#558000000
b00010111 !
b00010111 %
#560000000
b00011000 !
b00011000 %
#562000000
b00011001 !
b00011001 %
#564000000
b00011010 !
b00011010 %
#566000000
b00011011 !
b00011011 %
#568000000
b00011100 !
b00011100 %
#570000000
b00011101 !
b00011101 %
#572000000
b00011110 !
b00011110 %
#574000000
b00011111 !
b00011111 %
#576000000
b00100000 !
0#
b00100000 %
0&
#578000000
b00100001 !
b00100001 %
#580000000
b00100010 !
b00100010 %
#582000000
b00100011 !
b00100011 %
#584000000
b00100100 !
b00100100 %
#586000000
b00100101 !
b00100101 %
#588000000
b00100110 !
b00100110 %
#590000000
b00100111 !
b00100111 %
#592000000
b00101000 !
b00101000 %
#594000000
b00101001 !
b00101001 %
#596000000
b00101010 !
b00101010 %
#598000000
b00101011 !
b00101011 %
#600000000
b00101100 !
b00101100 %
#602000000
b00101101 !
b00101101 %
#604000000
b00101110 !
b00101110 %
#606000000
b00101111 !
b00101111 %
#608000000
b00110000 !
1#
b00110000 %
1&
#610000000
b00110001 !
b00110001 %
#612000000
b00110010 !
b00110010 %
#614000000
b00110011 !
b00110011 %
#616000000
b00110100 !
b00110100 %
#618000000
b00110101 !
b00110101 %
#620000000
b00110110 !
b00110110 %
#622000000
b00110111 !
b00110111 %
#624000000
b00111000 !
b00111000 %
#626000000
b00111001 !
b00111001 %
#628000000
b00111010 !
b00111010 %
#630000000
b00111011 !
b00111011 %
#632000000
b00111100 !
b00111100 %
#634000000
b00111101 !
b00111101 %
#636000000
b00111110 !
b00111110 %
#638000000
b00111111 !
b00111111 %
#640000000
b01000000 !
0#
b01000000 %
0&
#642000000
b01000001 !
b01000001 %
#644000000
b01000010 !
b01000010 %
#646000000
b01000011 !
b01000011 %
#648000000
b01000100 !
b01000100 %
#650000000
b01000101 !
b01000101 %
#652000000
b01000110 !
b01000110 %
#654000000
b01000111 !
b01000111 %
#656000000
b01001000 !
b01001000 %
#658000000
b01001001 !
b01001001 %
#660000000
b01001010 !
b01001010 %
#662000000
b01001011 !
b01001011 %
#664000000
b01001100 !
b01001100 %
#666000000
b01001101 !
b01001101 %
#668000000
b01001110 !
b01001110 %
#670000000
b01001111 !
b01001111 %
#672000000
b01010000 !
1#
b01010000 %
1&
#674000000
b01010001 !
b01010001 %
#676000000
b01010010 !
b01010010 %
#678000000
b01010011 !
b01010011 %
#680000000
b01010100 !
b01010100 %
#682000000
b01010101 !
b01010101 %
#684000000
b01010110 !
b01010110 %
#686000000
b01010111 !
b01010111 %
#688000000
b01011000 !
b01011000 %
#690000000
b01011001 !
b01011001 %
#692000000
b01011010 !
b01011010 %
#694000000
b01011011 !
b01011011 %
#696000000
b01011100 !
b01011100 %
#698000000
b01011101 !
b01011101 %
#700000000
b01011110 !
b01011110 %
#702000000
b01011111 !
b01011111 %
#704000000
b01100000 !
0#
b01100000 %
0&
#706000000
b01100001 !
b01100001 %
#708000000
b01100010 !
b01100010 %
#710000000
b01100011 !
b01100011 %
#712000000
b01100100 !
b01100100 %
#714000000
b01100101 !
b01100101 %
#716000000
b01100110 !
b01100110 %
#718000000
b01100111 !
b01100111 %
#720000000
b01101000 !
b01101000 %
#722000000
b01101001 !
b01101001 %
#724000000
b01101010 !
b01101010 %
#726000000
b01101011 !
b01101011 %
#728000000
b01101100 !
b01101100 %
#730000000
b01101101 !
b01101101 %
#732000000
b01101110 !
b01101110 %
#734000000
b01101111 !
b01101111 %
#736000000
b01110000 !
1#
b01110000 %
1&
#738000000
b01110001 !
b01110001 %
#740000000
b01110010 !
b01110010 %
#742000000
b01110011 !
b01110011 %
#744000000
b01110100 !
b01110100 %
#746000000
b01110101 !
b01110101 %
#748000000
b01110110 !
b01110110 %
#750000000
b01110111 !
b01110111 %
#752000000
b01111000 !
b01111000 %
#754000000
b01111001 !
b01111001 %
#756000000
b01111010 !
b01111010 %
#758000000
b01111011 !
b01111011 %
#760000000
b01111100 !
b01111100 %
#762000000
b01111101 !
b01111101 %
#764000000
b01111110 !
b01111110 %
#766000000
b01111111 !
b01111111 %
#768000000
b10000000 !
0#
b10000000 %
0&
#770000000
b10000001 !
b10000001 %
#772000000
b10000010 !
b10000010 %
#774000000
b10000011 !
b10000011 %
#776000000
b10000100 !
b10000100 %
#778000000
b10000101 !
b10000101 %
#780000000
b10000110 !
b10000110 %
#782000000
b10000111 !
b10000111 %
#784000000
b10001000 !
b10001000 %
#786000000
b10001001 !
b10001001 %
#788000000
b10001010 !
b10001010 %
#790000000
b10001011 !
b10001011 %
#792000000
b10001100 !
b10001100 %
#794000000
b10001101 !
b10001101 %
#796000000
b10001110 !
b10001110 %
#798000000
b10001111 !
b10001111 %
#800000000
b10010000 !
1#
b10010000 %
1&
#802000000
b10010001 !
b10010001 %
#804000000
b10010010 !
b10010010 %
#806000000
b10010011 !
b10010011 %
#808000000
b10010100 !
b10010100 %
#810000000
b10010101 !
b10010101 %
#812000000
b10010110 !
b10010110 %
#814000000
b10010111 !
b10010111 %
#816000000
b10011000 !
b10011000 %
#818000000
b10011001 !
b10011001 %
#820000000
b10011010 !
b10011010 %
#822000000
b10011011 !
b10011011 %
#824000000
b10011100 !
b10011100 %
#826000000
b10011101 !
b10011101 %
#828000000
b10011110 !
b10011110 %
#830000000
b10011111 !
b10011111 %
#832000000
b10100000 !
0#
b10100000 %
0&
#834000000
b10100001 !
b10100001 %
#836000000
b10100010 !
b10100010 %
#838000000
b10100011 !
b10100011 %
#840000000
b10100100 !
b10100100 %
#842000000
b10100101 !
b10100101 %
#844000000
b10100110 !
b10100110 %
#846000000
b10100111 !
b10100111 %
#848000000
b10101000 !
b10101000 %
#850000000
b10101001 !
b10101001 %
#852000000
b10101010 !
b10101010 %
#854000000
b10101011 !
b10101011 %
#856000000
b10101100 !
b10101100 %
#858000000
b10101101 !
b10101101 %
#860000000
b10101110 !
b10101110 %
#862000000
b10101111 !
b10101111 %
#864000000
b10110000 !
1#
b10110000 %
1&
#866000000
b10110001 !
b10110001 %
#868000000
b10110010 !
b10110010 %
#870000000
b10110011 !
b10110011 %
#872000000
b10110100 !
b10110100 %
#874000000
b10110101 !
b10110101 %
#876000000
b10110110 !
b10110110 %
#878000000
b10110111 !
b10110111 %
#880000000
b10111000 !
b10111000 %
#882000000
b10111001 !
b10111001 %
#884000000
b10111010 !
b10111010 %
#886000000
b10111011 !
b10111011 %
#888000000
b10111100 !
b10111100 %
#890000000
b10111101 !
b10111101 %
#892000000
b10111110 !
b10111110 %
#894000000
b10111111 !
b10111111 %
#896000000
b11000000 !
0#
b11000000 %
0&
#898000000
b11000001 !
b11000001 %
#900000000
b11000010 !
b11000010 %
#902000000
b11000011 !
b11000011 %
#904000000
b11000100 !
b11000100 %
#906000000
b11000101 !
b11000101 %
#908000000
b11000110 !
b11000110 %
#910000000
b11000111 !
b11000111 %
#912000000
b11001000 !
b11001000 %
#914000000
b11001001 !
b11001001 %
#916000000
b11001010 !
b11001010 %
#918000000
b11001011 !
b11001011 %
#920000000
b11001100 !
b11001100 %
#922000000
b11001101 !
b11001101 %
#924000000
b11001110 !
b11001110 %
#926000000
b11001111 !
b11001111 %
#928000000
b11010000 !
1#
b11010000 %
1&
#930000000
b11010001 !
b11010001 %
#932000000
b11010010 !
b11010010 %
#934000000
b11010011 !
b11010011 %
#936000000
b11010100 !
b11010100 %
#938000000
b11010101 !
b11010101 %
#940000000
b11010110 !
b11010110 %
#942000000
b11010111 !
b11010111 %
#944000000
b11011000 !
b11011000 %
#946000000
b11011001 !
b11011001 %
#948000000
b11011010 !
b11011010 %
#950000000
b11011011 !
b11011011 %
#952000000
b11011100 !
b11011100 %
#954000000
b11011101 !
b11011101 %
#956000000
b11011110 !
b11011110 %
#958000000
b11011111 !
b11011111 %
#960000000
b11100000 !
0#
b11100000 %
0&
#962000000
b11100001 !
b11100001 %
#964000000
b11100010 !
b11100010 %
#966000000
b11100011 !
b11100011 %
#968000000
b11100100 !
b11100100 %
#970000000
b11100101 !
b11100101 %
#972000000
b11100110 !
b11100110 %
#974000000
b11100111 !
b11100111 %
#976000000
b11101000 !
b11101000 %
#978000000
b11101001 !
b11101001 %
#980000000
b11101010 !
b11101010 %
#982000000
b11101011 !
b11101011 %
#984000000
b11101100 !
b11101100 %
#986000000
b11101101 !
b11101101 %
#988000000
b11101110 !
b11101110 %
#990000000
b11101111 !
b11101111 %
#992000000
b11110000 !
1#
b11110000 %
1&
#994000000
b11110001 !
b11110001 %
#996000000
b11110010 !
b11110010 %
#998000000
b11110011 !
b11110011 %
#1000000000
b11110100 !
b11110100 %
