problems/problem_9_2_3.vhd
-- NOTE: Change the file extension from .txt to .vhd

-- include libraries
LIBRARY IEEE;
USE ieee.std_logic_1164.ALL;

ENTITY problem_9_2_3 IS
    PORT (
        clock : IN STD_LOGIC;
        din : IN STD_LOGIC;
        reset : IN STD_LOGIC;
        dout : OUT STD_LOGIC);
END ENTITY;

ARCHITECTURE RTL OF problem_9_2_3 IS
    TYPE State_type IS (S0, S1, S2, S3);
    SIGNAL state : State_Type;
BEGIN

    PROCESS (clock, reset)
    BEGIN
        IF (reset = '1') THEN
            State <= S0;

        ELSIF rising_edge(clock) THEN
            CASE State IS
                WHEN S0 =>
                    IF din = '0' THEN
                        dout <= '0';
                        State <= S0;
                    END IF;
                    IF din = '1' THEN
                        dout <= '1';
                        State <= S1;
                    END IF;

                WHEN S1 =>
                    IF din = '1' THEN
                        dout <= '0';
                        State <= S3;
                    END IF;
                    IF din = '0' THEN
                        dout <= '1';
                        State <= S2;
                    END IF;

                WHEN S2 =>
                    IF din = '0' THEN
                        dout <= '0';
                        State <= S0;
                    END IF;
                    IF din = '1' THEN
                        dout <= '1';
                        State <= S3;
                    END IF;

                WHEN S3 =>
                    IF din = '0' THEN
                        dout <= '0';
                        State <= S3;
                    END IF;
                    IF din = '1' THEN
                        dout <= '1';
                        State <= S0;
                    END IF;
                WHEN OTHERS =>
                    State <= S0;
            END CASE;
        END IF;
    END PROCESS;

END rtl;

problems/problem_9_2_3_test.vhd
LIBRARY ieee;
USE ieee.std_logic_1164.ALL;

ENTITY problem_9_2_3_test IS
END problem_9_2_3_test;

ARCHITECTURE behavior OF problem_9_2_3_test IS

    SIGNAL Din : STD_LOGIC := '0';
    SIGNAL Clock : STD_LOGIC := '0';
    SIGNAL Reset : STD_LOGIC := '0';
    SIGNAL Dout : STD_LOGIC;

    CONSTANT Clock_period : TIME := 10 ns;

    COMPONENT problem_9_2_3
        PORT (
            Din : IN STD_LOGIC;
            Clock : IN STD_LOGIC;
            Reset : IN STD_LOGIC;
            Dout : OUT STD_LOGIC
        );
    END COMPONENT;

BEGIN
    UUT : ENTITY work.problem_9_2_3 PORT MAP(
        Din => Din,
        Clock => Clock,
        Reset => Reset,
        Dout => Dout
        );

    -- Clock process definitions
    Clock_process : PROCESS
    BEGIN
        Clock <= '0';
        WAIT FOR Clock_period/2;
        Clock <= '1';
        WAIT FOR Clock_period/2;
    END PROCESS;

    testB : PROCESS
    BEGIN
        Din <= '1';
        WAIT FOR Clock_period * 2;
        Din <= '0';
        WAIT FOR Clock_period * 2;
    END PROCESS;

END;

waves/problem_9_2_3_test.vcd
$date
  Mon Jun  6 19:16:34 2022
$end
$version
  GHDL v0
$end
$timescale
  1 fs
$end
$scope module standard $end
$upscope $end
$scope module textio $end
$upscope $end
$scope module std_logic_1164 $end
$upscope $end
$scope module problem_9_2_3_test $end
$var reg 1 ! din $end
$var reg 1 " clock $end
$var reg 1 # reset $end
$var reg 1 $ dout $end
$scope module uut $end
$var reg 1 % clock $end
$var reg 1 & din $end
$var reg 1 ' reset $end
$var reg 1 ( dout $end
$comment state is not handled $end
$upscope $end
$upscope $end
$enddefinitions $end
#0
1!
0"
0#
U$
0%
1&
0'
U(
#5000000
1"
1$
1%
1(
#10000000
0"
0%
#15000000
1"
0$
1%
0(
#20000000
0!
0"
0%
0&
#25000000
1"
1%
#30000000
0"
0%
#35000000
1"
1%
#40000000
1!
0"
0%
1&
#45000000
1"
1$
1%
1(
#50000000
0"
0%
#55000000
1"
1%
#60000000
0!
0"
0%
0&
#65000000
1"
1%
#70000000
0"
0%
#75000000
1"
0$
1%
0(
#80000000
1!
0"
0%
1&
#85000000
1"
1$
1%
1(
#90000000
0"
0%
#95000000
1"
0$
1%
0(
#100000000
0!
0"
0%
0&
#105000000
1"
1%
#110000000
0"
0%
#115000000
1"
1%
#120000000
1!
0"
0%
1&
#125000000
1"
1$
1%
1(
#130000000
0"
0%
#135000000
1"
1%
#140000000
0!
0"
0%
0&
#145000000
1"
1%
#150000000
0"
0%
#155000000
1"
0$
1%
0(
#160000000
1!
0"
0%
1&
#165000000
1"
1$
1%
1(
#170000000
0"
0%
#175000000
1"
0$
1%
0(
#180000000
0!
0"
0%
0&
#185000000
1"
1%
#190000000
0"
0%
#195000000
1"
1%
#200000000
1!
0"
0%
1&
#205000000
1"
1$
1%
1(
#210000000
0"
0%
#215000000
1"
1%
#220000000
0!
0"
0%
0&
#225000000
1"
1%
#230000000
0"
0%
#235000000
1"
0$
1%
0(
#240000000
1!
0"
0%
1&
#245000000
1"
1$
1%
1(
#250000000
0"
0%
#255000000
1"
0$
1%
0(
#260000000
0!
0"
0%
0&
#265000000
1"
1%
#270000000
0"
0%
#275000000
1"
1%
#280000000
1!
0"
0%
1&
#285000000
1"
1$
1%
1(
#290000000
0"
0%
#295000000
1"
1%
#300000000
0!
0"
0%
0&
#305000000
1"
1%
#310000000
0"
0%
#315000000
1"
0$
1%
0(
#320000000
1!
0"
0%
1&
#325000000
1"
1$
1%
1(
#330000000
0"
0%
#335000000
1"
0$
1%
0(
#340000000
0!
0"
0%
0&
#345000000
1"
1%
#350000000
0"
0%
#355000000
1"
1%
#360000000
1!
0"
0%
1&
#365000000
1"
1$
1%
1(
#370000000
0"
0%
#375000000
1"
1%
#380000000
0!
0"
0%
0&
#385000000
1"
1%
#390000000
0"
0%
#395000000
1"
0$
1%
0(
#400000000
1!
0"
0%
1&
#405000000
1"
1$
1%
1(
#410000000
0"
0%
#415000000
1"
0$
1%
0(
#420000000
0!
0"
0%
0&
#425000000
1"
1%
#430000000
0"
0%
#435000000
1"
1%
#440000000
1!
0"
0%
1&
#445000000
1"
1$
1%
1(
#450000000
0"
0%
#455000000
1"
1%
#460000000
0!
0"
0%
0&
#465000000
1"
1%
#470000000
0"
0%
#475000000
1"
0$
1%
0(
#480000000
1!
0"
0%
1&
#485000000
1"
1$
1%
1(
#490000000
0"
0%
#495000000
1"
0$
1%
0(
#500000000
0!
0"
0%
0&
#505000000
1"
1%
#510000000
0"
0%
#515000000
1"
1%
#520000000
1!
0"
0%
1&
#525000000
1"
1$
1%
1(
#530000000
0"
0%
#535000000
1"
1%
#540000000
0!
0"
0%
0&
#545000000
1"
1%
#550000000
0"
0%
#555000000
1"
0$
1%
0(
#560000000
1!
0"
0%
1&
#565000000
1"
1$
1%
1(
#570000000
0"
0%
#575000000
1"
0$
1%
0(
#580000000
0!
0"
0%
0&
#585000000
1"
1%
#590000000
0"
0%
#595000000
1"
1%
#600000000
1!
0"
0%
1&
#605000000
1"
1$
1%
1(
#610000000
0"
0%
#615000000
1"
1%
#620000000
0!
0"
0%
0&
#625000000
1"
1%
#630000000
0"
0%
#635000000
1"
0$
1%
0(
#640000000
1!
0"
0%
1&
#645000000
1"
1$
1%
1(
#650000000
0"
0%
#655000000
1"
0$
1%
0(
#660000000
0!
0"
0%
0&
#665000000
1"
1%
#670000000
0"
0%
#675000000
1"
1%
#680000000
1!
0"
0%
1&
#685000000
1"
1$
1%
1(
#690000000
0"
0%
#695000000
1"
1%
#700000000
0!
0"
0%
0&
#705000000
1"
1%
#710000000
0"
0%
#715000000
1"
0$
1%
0(
#720000000
1!
0"
0%
1&
#725000000
1"
1$
1%
1(
#730000000
0"
0%
#735000000
1"
0$
1%
0(
#740000000
0!
0"
0%
0&
#745000000
1"
1%
#750000000
0"
0%
#755000000
1"
1%
#760000000
1!
0"
0%
1&
#765000000
1"
1$
1%
1(
#770000000
0"
0%
#775000000
1"
1%
#780000000
0!
0"
0%
0&
#785000000
1"
1%
#790000000
0"
0%
#795000000
1"
0$
1%
0(
#800000000
1!
0"
0%
1&
#805000000
1"
1$
1%
1(
#810000000
0"
0%
#815000000
1"
0$
1%
0(
#820000000
0!
0"
0%
0&
#825000000
1"
1%
#830000000
0"
0%
#835000000
1"
1%
#840000000
1!
0"
0%
1&
#845000000
1"
1$
1%
1(
#850000000
0"
0%
#855000000
1"
1%
#860000000
0!
0"
0%
0&
#865000000
1"
1%
#870000000
0"
0%
#875000000
1"
0$
1%
0(
#880000000
1!
0"
0%
1&
#885000000
1"
1$
1%
1(
#890000000
0"
0%
#895000000
1"
0$
1%
0(
#900000000
0!
0"
0%
0&
#905000000
1"
1%
#910000000
0"
0%
#915000000
1"
1%
#920000000
1!
0"
0%
1&
#925000000
1"
1$
1%
1(
#930000000
0"
0%
#935000000
1"
1%
#940000000
0!
0"
0%
0&
#945000000
1"
1%
#950000000
0"
0%
#955000000
1"
0$
1%
0(
#960000000
1!
0"
0%
1&
#965000000
1"
1$
1%
1(
#970000000
0"
0%
#975000000
1"
0$
1%
0(
#980000000
0!
0"
0%
0&
#985000000
1"
1%
#990000000
0"
0%
#995000000
1"
1%
#1000000000
1!
0"
0%
1&
