problems/problem_5_2_1.vhd
LIBRARY ieee;
USE ieee.std_logic_1164.ALL;
USE ieee.numeric_std.ALL;
USE ieee.math_real.ALL;

ENTITY problem_5_2_1 IS
    PORT (
        abcd : IN STD_LOGIC_VECTOR(3 DOWNTO 0);
        f : OUT STD_LOGIC
    );
END ENTITY problem_5_2_1;

ARCHITECTURE rtl OF problem_5_2_1 IS
BEGIN

    PROCESS (abcd)
    BEGIN
        IF (abcd = "0001" OR abcd = "0011" OR abcd = "1001" OR abcd = "1011")
            THEN
            F <= '1';
        ELSE
            F <= '0';
        END IF;
    

    END PROCESS;
END ARCHITECTURE;

problems/problem_5_2_1_test.vhd
LIBRARY IEEE;
USE IEEE.STD_LOGIC_1164.ALL;
USE IEEE.STD_LOGIC_ARITH.ALL;
USE IEEE.STD_LOGIC_UNSIGNED.ALL;
USE IEEE.NUMERIC_STD.ALL;

ENTITY problem_5_2_1_test IS
END problem_5_2_1_test;

ARCHITECTURE behavior OF problem_5_2_1_test IS
    SIGNAL abcd : STD_LOGIC_VECTOR(3 DOWNTO 0) := (OTHERS => '0');
    SIGNAL f : STD_LOGIC := '0';

BEGIN
    UUT : ENTITY work.problem_5_2_1 PORT MAP(abcd, f);

    tb : PROCESS
    BEGIN
        FOR j IN 0 TO 2 ** abcd'length - 1 LOOP
            abcd <= STD_LOGIC_VECTOR(to_unsigned(j, abcd'length));
            WAIT FOR 2 ns;
        END LOOP;
    END PROCESS tb;
END;

waves/problem_5_2_1_test.vcd
$date
  Sun May 15 21:28:51 2022
$end
$version
  GHDL v0
$end
$timescale
  1 fs
$end
$scope module standard $end
$upscope $end
$scope module textio $end
$upscope $end
$scope module std_logic_1164 $end
$upscope $end
$scope module std_logic_arith $end
$upscope $end
$scope module std_logic_unsigned $end
$upscope $end
$scope module numeric_std $end
$upscope $end
$scope module math_real $end
$upscope $end
$scope module problem_5_2_1_test $end
$var reg 4 ! abcd[3:0] $end
$var reg 1 " f $end
$scope module uut $end
$var reg 4 # abcd[3:0] $end
$var reg 1 $ f $end
$upscope $end
$upscope $end
$enddefinitions $end
#0
b0000 !
0"
b0000 #
0$
#2000000
b0001 !
1"
b0001 #
1$
#4000000
b0010 !
0"
b0010 #
0$
#6000000
b0011 !
1"
b0011 #
1$
#8000000
b0100 !
0"
b0100 #
0$
#10000000
b0101 !
b0101 #
#12000000
b0110 !
b0110 #
#14000000
b0111 !
b0111 #
#16000000
b1000 !
b1000 #
#18000000
b1001 !
1"
b1001 #
1$
#20000000
b1010 !
0"
b1010 #
0$
#22000000
b1011 !
1"
b1011 #
1$
#24000000
b1100 !
0"
b1100 #
0$
#26000000
b1101 !
b1101 #
#28000000
b1110 !
b1110 #
#30000000
b1111 !
b1111 #
#32000000
b0000 !
b0000 #
#34000000
b0001 !
1"
b0001 #
1$
#36000000
b0010 !
0"
b0010 #
0$
#38000000
b0011 !
1"
b0011 #
1$
#40000000
b0100 !
0"
b0100 #
0$
#42000000
b0101 !
b0101 #
#44000000
b0110 !
b0110 #
#46000000
b0111 !
b0111 #
#48000000
b1000 !
b1000 #
#50000000
b1001 !
1"
b1001 #
1$
#52000000
b1010 !
0"
b1010 #
0$
#54000000
b1011 !
1"
b1011 #
1$
#56000000
b1100 !
0"
b1100 #
0$
#58000000
b1101 !
b1101 #
#60000000
b1110 !
b1110 #
#62000000
b1111 !
b1111 #
#64000000
b0000 !
b0000 #
#66000000
b0001 !
1"
b0001 #
1$
#68000000
b0010 !
0"
b0010 #
0$
#70000000
b0011 !
1"
b0011 #
1$
#72000000
b0100 !
0"
b0100 #
0$
#74000000
b0101 !
b0101 #
#76000000
b0110 !
b0110 #
#78000000
b0111 !
b0111 #
#80000000
b1000 !
b1000 #
#82000000
b1001 !
1"
b1001 #
1$
#84000000
b1010 !
0"
b1010 #
0$
#86000000
b1011 !
1"
b1011 #
1$
#88000000
b1100 !
0"
b1100 #
0$
#90000000
b1101 !
b1101 #
#92000000
b1110 !
b1110 #
#94000000
b1111 !
b1111 #
#96000000
b0000 !
b0000 #
#98000000
b0001 !
1"
b0001 #
1$
#100000000
b0010 !
0"
b0010 #
0$
#102000000
b0011 !
1"
b0011 #
1$
#104000000
b0100 !
0"
b0100 #
0$
#106000000
b0101 !
b0101 #
#108000000
b0110 !
b0110 #
#110000000
b0111 !
b0111 #
#112000000
b1000 !
b1000 #
#114000000
b1001 !
1"
b1001 #
1$
#116000000
b1010 !
0"
b1010 #
0$
#118000000
b1011 !
1"
b1011 #
1$
#120000000
b1100 !
0"
b1100 #
0$
#122000000
b1101 !
b1101 #
#124000000
b1110 !
b1110 #
#126000000
b1111 !
b1111 #
#128000000
b0000 !
b0000 #
#130000000
b0001 !
1"
b0001 #
1$
#132000000
b0010 !
0"
b0010 #
0$
#134000000
b0011 !
1"
b0011 #
1$
#136000000
b0100 !
0"
b0100 #
0$
#138000000
b0101 !
b0101 #
#140000000
b0110 !
b0110 #
#142000000
b0111 !
b0111 #
#144000000
b1000 !
b1000 #
#146000000
b1001 !
1"
b1001 #
1$
#148000000
b1010 !
0"
b1010 #
0$
#150000000
b1011 !
1"
b1011 #
1$
#152000000
b1100 !
0"
b1100 #
0$
#154000000
b1101 !
b1101 #
#156000000
b1110 !
b1110 #
#158000000
b1111 !
b1111 #
#160000000
b0000 !
b0000 #
#162000000
b0001 !
1"
b0001 #
1$
#164000000
b0010 !
0"
b0010 #
0$
#166000000
b0011 !
1"
b0011 #
1$
#168000000
b0100 !
0"
b0100 #
0$
#170000000
b0101 !
b0101 #
#172000000
b0110 !
b0110 #
#174000000
b0111 !
b0111 #
#176000000
b1000 !
b1000 #
#178000000
b1001 !
1"
b1001 #
1$
#180000000
b1010 !
0"
b1010 #
0$
#182000000
b1011 !
1"
b1011 #
1$
#184000000
b1100 !
0"
b1100 #
0$
#186000000
b1101 !
b1101 #
#188000000
b1110 !
b1110 #
#190000000
b1111 !
b1111 #
#192000000
b0000 !
b0000 #
#194000000
b0001 !
1"
b0001 #
1$
#196000000
b0010 !
0"
b0010 #
0$
#198000000
b0011 !
1"
b0011 #
1$
#200000000
b0100 !
0"
b0100 #
0$
#202000000
b0101 !
b0101 #
#204000000
b0110 !
b0110 #
#206000000
b0111 !
b0111 #
#208000000
b1000 !
b1000 #
#210000000
b1001 !
1"
b1001 #
1$
#212000000
b1010 !
0"
b1010 #
0$
#214000000
b1011 !
1"
b1011 #
1$
#216000000
b1100 !
0"
b1100 #
0$
#218000000
b1101 !
b1101 #
#220000000
b1110 !
b1110 #
#222000000
b1111 !
b1111 #
#224000000
b0000 !
b0000 #
#226000000
b0001 !
1"
b0001 #
1$
#228000000
b0010 !
0"
b0010 #
0$
#230000000
b0011 !
1"
b0011 #
1$
#232000000
b0100 !
0"
b0100 #
0$
#234000000
b0101 !
b0101 #
#236000000
b0110 !
b0110 #
#238000000
b0111 !
b0111 #
#240000000
b1000 !
b1000 #
#242000000
b1001 !
1"
b1001 #
1$
#244000000
b1010 !
0"
b1010 #
0$
#246000000
b1011 !
1"
b1011 #
1$
#248000000
b1100 !
0"
b1100 #
0$
#250000000
b1101 !
b1101 #
#252000000
b1110 !
b1110 #
#254000000
b1111 !
b1111 #
#256000000
b0000 !
b0000 #
#258000000
b0001 !
1"
b0001 #
1$
#260000000
b0010 !
0"
b0010 #
0$
#262000000
b0011 !
1"
b0011 #
1$
#264000000
b0100 !
0"
b0100 #
0$
#266000000
b0101 !
b0101 #
#268000000
b0110 !
b0110 #
#270000000
b0111 !
b0111 #
#272000000
b1000 !
b1000 #
#274000000
b1001 !
1"
b1001 #
1$
#276000000
b1010 !
0"
b1010 #
0$
#278000000
b1011 !
1"
b1011 #
1$
#280000000
b1100 !
0"
b1100 #
0$
#282000000
b1101 !
b1101 #
#284000000
b1110 !
b1110 #
#286000000
b1111 !
b1111 #
#288000000
b0000 !
b0000 #
#290000000
b0001 !
1"
b0001 #
1$
#292000000
b0010 !
0"
b0010 #
0$
#294000000
b0011 !
1"
b0011 #
1$
#296000000
b0100 !
0"
b0100 #
0$
#298000000
b0101 !
b0101 #
#300000000
b0110 !
b0110 #
#302000000
b0111 !
b0111 #
#304000000
b1000 !
b1000 #
#306000000
b1001 !
1"
b1001 #
1$
#308000000
b1010 !
0"
b1010 #
0$
#310000000
b1011 !
1"
b1011 #
1$
#312000000
b1100 !
0"
b1100 #
0$
#314000000
b1101 !
b1101 #
#316000000
b1110 !
b1110 #
#318000000
b1111 !
b1111 #
#320000000
b0000 !
b0000 #
#322000000
b0001 !
1"
b0001 #
1$
#324000000
b0010 !
0"
b0010 #
0$
#326000000
b0011 !
1"
b0011 #
1$
#328000000
b0100 !
0"
b0100 #
0$
#330000000
b0101 !
b0101 #
#332000000
b0110 !
b0110 #
#334000000
b0111 !
b0111 #
#336000000
b1000 !
b1000 #
#338000000
b1001 !
1"
b1001 #
1$
#340000000
b1010 !
0"
b1010 #
0$
#342000000
b1011 !
1"
b1011 #
1$
#344000000
b1100 !
0"
b1100 #
0$
#346000000
b1101 !
b1101 #
#348000000
b1110 !
b1110 #
#350000000
b1111 !
b1111 #
#352000000
b0000 !
b0000 #
#354000000
b0001 !
1"
b0001 #
1$
#356000000
b0010 !
0"
b0010 #
0$
#358000000
b0011 !
1"
b0011 #
1$
#360000000
b0100 !
0"
b0100 #
0$
#362000000
b0101 !
b0101 #
#364000000
b0110 !
b0110 #
#366000000
b0111 !
b0111 #
#368000000
b1000 !
b1000 #
#370000000
b1001 !
1"
b1001 #
1$
#372000000
b1010 !
0"
b1010 #
0$
#374000000
b1011 !
1"
b1011 #
1$
#376000000
b1100 !
0"
b1100 #
0$
#378000000
b1101 !
b1101 #
#380000000
b1110 !
b1110 #
#382000000
b1111 !
b1111 #
#384000000
b0000 !
b0000 #
#386000000
b0001 !
1"
b0001 #
1$
#388000000
b0010 !
0"
b0010 #
0$
#390000000
b0011 !
1"
b0011 #
1$
#392000000
b0100 !
0"
b0100 #
0$
#394000000
b0101 !
b0101 #
#396000000
b0110 !
b0110 #
#398000000
b0111 !
b0111 #
#400000000
b1000 !
b1000 #
#402000000
b1001 !
1"
b1001 #
1$
#404000000
b1010 !
0"
b1010 #
0$
#406000000
b1011 !
1"
b1011 #
1$
#408000000
b1100 !
0"
b1100 #
0$
#410000000
b1101 !
b1101 #
#412000000
b1110 !
b1110 #
#414000000
b1111 !
b1111 #
#416000000
b0000 !
b0000 #
#418000000
b0001 !
1"
b0001 #
1$
#420000000
b0010 !
0"
b0010 #
0$
#422000000
b0011 !
1"
b0011 #
1$
#424000000
b0100 !
0"
b0100 #
0$
#426000000
b0101 !
b0101 #
#428000000
b0110 !
b0110 #
#430000000
b0111 !
b0111 #
#432000000
b1000 !
b1000 #
#434000000
b1001 !
1"
b1001 #
1$
#436000000
b1010 !
0"
b1010 #
0$
#438000000
b1011 !
1"
b1011 #
1$
#440000000
b1100 !
0"
b1100 #
0$
#442000000
b1101 !
b1101 #
#444000000
b1110 !
b1110 #
#446000000
b1111 !
b1111 #
#448000000
b0000 !
b0000 #
#450000000
b0001 !
1"
b0001 #
1$
#452000000
b0010 !
0"
b0010 #
0$
#454000000
b0011 !
1"
b0011 #
1$
#456000000
b0100 !
0"
b0100 #
0$
#458000000
b0101 !
b0101 #
#460000000
b0110 !
b0110 #
#462000000
b0111 !
b0111 #
#464000000
b1000 !
b1000 #
#466000000
b1001 !
1"
b1001 #
1$
#468000000
b1010 !
0"
b1010 #
0$
#470000000
b1011 !
1"
b1011 #
1$
#472000000
b1100 !
0"
b1100 #
0$
#474000000
b1101 !
b1101 #
#476000000
b1110 !
b1110 #
#478000000
b1111 !
b1111 #
#480000000
b0000 !
b0000 #
#482000000
b0001 !
1"
b0001 #
1$
#484000000
b0010 !
0"
b0010 #
0$
#486000000
b0011 !
1"
b0011 #
1$
#488000000
b0100 !
0"
b0100 #
0$
#490000000
b0101 !
b0101 #
#492000000
b0110 !
b0110 #
#494000000
b0111 !
b0111 #
#496000000
b1000 !
b1000 #
#498000000
b1001 !
1"
b1001 #
1$
#500000000
b1010 !
0"
b1010 #
0$
#502000000
b1011 !
1"
b1011 #
1$
#504000000
b1100 !
0"
b1100 #
0$
#506000000
b1101 !
b1101 #
#508000000
b1110 !
b1110 #
#510000000
b1111 !
b1111 #
#512000000
b0000 !
b0000 #
#514000000
b0001 !
1"
b0001 #
1$
#516000000
b0010 !
0"
b0010 #
0$
#518000000
b0011 !
1"
b0011 #
1$
#520000000
b0100 !
0"
b0100 #
0$
#522000000
b0101 !
b0101 #
#524000000
b0110 !
b0110 #
#526000000
b0111 !
b0111 #
#528000000
b1000 !
b1000 #
#530000000
b1001 !
1"
b1001 #
1$
#532000000
b1010 !
0"
b1010 #
0$
#534000000
b1011 !
1"
b1011 #
1$
#536000000
b1100 !
0"
b1100 #
0$
#538000000
b1101 !
b1101 #
#540000000
b1110 !
b1110 #
#542000000
b1111 !
b1111 #
#544000000
b0000 !
b0000 #
#546000000
b0001 !
1"
b0001 #
1$
#548000000
b0010 !
0"
b0010 #
0$
#550000000
b0011 !
1"
b0011 #
1$
#552000000
b0100 !
0"
b0100 #
0$
#554000000
b0101 !
b0101 #
#556000000
b0110 !
b0110 #
#558000000
b0111 !
b0111 #
#560000000
b1000 !
b1000 #
#562000000
b1001 !
1"
b1001 #
1$
#564000000
b1010 !
0"
b1010 #
0$
#566000000
b1011 !
1"
b1011 #
1$
#568000000
b1100 !
0"
b1100 #
0$
#570000000
b1101 !
b1101 #
#572000000
b1110 !
b1110 #
#574000000
b1111 !
b1111 #
#576000000
b0000 !
b0000 #
#578000000
b0001 !
1"
b0001 #
1$
#580000000
b0010 !
0"
b0010 #
0$
#582000000
b0011 !
1"
b0011 #
1$
#584000000
b0100 !
0"
b0100 #
0$
#586000000
b0101 !
b0101 #
#588000000
b0110 !
b0110 #
#590000000
b0111 !
b0111 #
#592000000
b1000 !
b1000 #
#594000000
b1001 !
1"
b1001 #
1$
#596000000
b1010 !
0"
b1010 #
0$
#598000000
b1011 !
1"
b1011 #
1$
#600000000
b1100 !
0"
b1100 #
0$
#602000000
b1101 !
b1101 #
#604000000
b1110 !
b1110 #
#606000000
b1111 !
b1111 #
#608000000
b0000 !
b0000 #
#610000000
b0001 !
1"
b0001 #
1$
#612000000
b0010 !
0"
b0010 #
0$
#614000000
b0011 !
1"
b0011 #
1$
#616000000
b0100 !
0"
b0100 #
0$
#618000000
b0101 !
b0101 #
#620000000
b0110 !
b0110 #
#622000000
b0111 !
b0111 #
#624000000
b1000 !
b1000 #
#626000000
b1001 !
1"
b1001 #
1$
#628000000
b1010 !
0"
b1010 #
0$
#630000000
b1011 !
1"
b1011 #
1$
#632000000
b1100 !
0"
b1100 #
0$
#634000000
b1101 !
b1101 #
#636000000
b1110 !
b1110 #
#638000000
b1111 !
b1111 #
#640000000
b0000 !
b0000 #
#642000000
b0001 !
1"
b0001 #
1$
#644000000
b0010 !
0"
b0010 #
0$
#646000000
b0011 !
1"
b0011 #
1$
#648000000
b0100 !
0"
b0100 #
0$
#650000000
b0101 !
b0101 #
#652000000
b0110 !
b0110 #
#654000000
b0111 !
b0111 #
#656000000
b1000 !
b1000 #
#658000000
b1001 !
1"
b1001 #
1$
#660000000
b1010 !
0"
b1010 #
0$
#662000000
b1011 !
1"
b1011 #
1$
#664000000
b1100 !
0"
b1100 #
0$
#666000000
b1101 !
b1101 #
#668000000
b1110 !
b1110 #
#670000000
b1111 !
b1111 #
#672000000
b0000 !
b0000 #
#674000000
b0001 !
1"
b0001 #
1$
#676000000
b0010 !
0"
b0010 #
0$
#678000000
b0011 !
1"
b0011 #
1$
#680000000
b0100 !
0"
b0100 #
0$
#682000000
b0101 !
b0101 #
#684000000
b0110 !
b0110 #
#686000000
b0111 !
b0111 #
#688000000
b1000 !
b1000 #
#690000000
b1001 !
1"
b1001 #
1$
#692000000
b1010 !
0"
b1010 #
0$
#694000000
b1011 !
1"
b1011 #
1$
#696000000
b1100 !
0"
b1100 #
0$
#698000000
b1101 !
b1101 #
#700000000
b1110 !
b1110 #
#702000000
b1111 !
b1111 #
#704000000
b0000 !
b0000 #
#706000000
b0001 !
1"
b0001 #
1$
#708000000
b0010 !
0"
b0010 #
0$
#710000000
b0011 !
1"
b0011 #
1$
#712000000
b0100 !
0"
b0100 #
0$
#714000000
b0101 !
b0101 #
#716000000
b0110 !
b0110 #
#718000000
b0111 !
b0111 #
#720000000
b1000 !
b1000 #
#722000000
b1001 !
1"
b1001 #
1$
#724000000
b1010 !
0"
b1010 #
0$
#726000000
b1011 !
1"
b1011 #
1$
#728000000
b1100 !
0"
b1100 #
0$
#730000000
b1101 !
b1101 #
#732000000
b1110 !
b1110 #
#734000000
b1111 !
b1111 #
#736000000
b0000 !
b0000 #
#738000000
b0001 !
1"
b0001 #
1$
#740000000
b0010 !
0"
b0010 #
0$
#742000000
b0011 !
1"
b0011 #
1$
#744000000
b0100 !
0"
b0100 #
0$
#746000000
b0101 !
b0101 #
#748000000
b0110 !
b0110 #
#750000000
b0111 !
b0111 #
#752000000
b1000 !
b1000 #
#754000000
b1001 !
1"
b1001 #
1$
#756000000
b1010 !
0"
b1010 #
0$
#758000000
b1011 !
1"
b1011 #
1$
#760000000
b1100 !
0"
b1100 #
0$
#762000000
b1101 !
b1101 #
#764000000
b1110 !
b1110 #
#766000000
b1111 !
b1111 #
#768000000
b0000 !
b0000 #
#770000000
b0001 !
1"
b0001 #
1$
#772000000
b0010 !
0"
b0010 #
0$
#774000000
b0011 !
1"
b0011 #
1$
#776000000
b0100 !
0"
b0100 #
0$
#778000000
b0101 !
b0101 #
#780000000
b0110 !
b0110 #
#782000000
b0111 !
b0111 #
#784000000
b1000 !
b1000 #
#786000000
b1001 !
1"
b1001 #
1$
#788000000
b1010 !
0"
b1010 #
0$
#790000000
b1011 !
1"
b1011 #
1$
#792000000
b1100 !
0"
b1100 #
0$
#794000000
b1101 !
b1101 #
#796000000
b1110 !
b1110 #
#798000000
b1111 !
b1111 #
#800000000
b0000 !
b0000 #
#802000000
b0001 !
1"
b0001 #
1$
#804000000
b0010 !
0"
b0010 #
0$
#806000000
b0011 !
1"
b0011 #
1$
#808000000
b0100 !
0"
b0100 #
0$
#810000000
b0101 !
b0101 #
#812000000
b0110 !
b0110 #
#814000000
b0111 !
b0111 #
#816000000
b1000 !
b1000 #
#818000000
b1001 !
1"
b1001 #
1$
#820000000
b1010 !
0"
b1010 #
0$
#822000000
b1011 !
1"
b1011 #
1$
#824000000
b1100 !
0"
b1100 #
0$
#826000000
b1101 !
b1101 #
#828000000
b1110 !
b1110 #
#830000000
b1111 !
b1111 #
#832000000
b0000 !
b0000 #
#834000000
b0001 !
1"
b0001 #
1$
#836000000
b0010 !
0"
b0010 #
0$
#838000000
b0011 !
1"
b0011 #
1$
#840000000
b0100 !
0"
b0100 #
0$
#842000000
b0101 !
b0101 #
#844000000
b0110 !
b0110 #
#846000000
b0111 !
b0111 #
#848000000
b1000 !
b1000 #
#850000000
b1001 !
1"
b1001 #
1$
#852000000
b1010 !
0"
b1010 #
0$
#854000000
b1011 !
1"
b1011 #
1$
#856000000
b1100 !
0"
b1100 #
0$
#858000000
b1101 !
b1101 #
#860000000
b1110 !
b1110 #
#862000000
b1111 !
b1111 #
#864000000
b0000 !
b0000 #
#866000000
b0001 !
1"
b0001 #
1$
#868000000
b0010 !
0"
b0010 #
0$
#870000000
b0011 !
1"
b0011 #
1$
#872000000
b0100 !
0"
b0100 #
0$
#874000000
b0101 !
b0101 #
#876000000
b0110 !
b0110 #
#878000000
b0111 !
b0111 #
#880000000
b1000 !
b1000 #
#882000000
b1001 !
1"
b1001 #
1$
#884000000
b1010 !
0"
b1010 #
0$
#886000000
b1011 !
1"
b1011 #
1$
#888000000
b1100 !
0"
b1100 #
0$
#890000000
b1101 !
b1101 #
#892000000
b1110 !
b1110 #
#894000000
b1111 !
b1111 #
#896000000
b0000 !
b0000 #
#898000000
b0001 !
1"
b0001 #
1$
#900000000
b0010 !
0"
b0010 #
0$
#902000000
b0011 !
1"
b0011 #
1$
#904000000
b0100 !
0"
b0100 #
0$
#906000000
b0101 !
b0101 #
#908000000
b0110 !
b0110 #
#910000000
b0111 !
b0111 #
#912000000
b1000 !
b1000 #
#914000000
b1001 !
1"
b1001 #
1$
#916000000
b1010 !
0"
b1010 #
0$
#918000000
b1011 !
1"
b1011 #
1$
#920000000
b1100 !
0"
b1100 #
0$
#922000000
b1101 !
b1101 #
#924000000
b1110 !
b1110 #
#926000000
b1111 !
b1111 #
#928000000
b0000 !
b0000 #
#930000000
b0001 !
1"
b0001 #
1$
#932000000
b0010 !
0"
b0010 #
0$
#934000000
b0011 !
1"
b0011 #
1$
#936000000
b0100 !
0"
b0100 #
0$
#938000000
b0101 !
b0101 #
#940000000
b0110 !
b0110 #
#942000000
b0111 !
b0111 #
#944000000
b1000 !
b1000 #
#946000000
b1001 !
1"
b1001 #
1$
#948000000
b1010 !
0"
b1010 #
0$
#950000000
b1011 !
1"
b1011 #
1$
#952000000
b1100 !
0"
b1100 #
0$
#954000000
b1101 !
b1101 #
#956000000
b1110 !
b1110 #
#958000000
b1111 !
b1111 #
#960000000
b0000 !
b0000 #
#962000000
b0001 !
1"
b0001 #
1$
#964000000
b0010 !
0"
b0010 #
0$
#966000000
b0011 !
1"
b0011 #
1$
#968000000
b0100 !
0"
b0100 #
0$
#970000000
b0101 !
b0101 #
#972000000
b0110 !
b0110 #
#974000000
b0111 !
b0111 #
#976000000
b1000 !
b1000 #
#978000000
b1001 !
1"
b1001 #
1$
#980000000
b1010 !
0"
b1010 #
0$
#982000000
b1011 !
1"
b1011 #
1$
#984000000
b1100 !
0"
b1100 #
0$
#986000000
b1101 !
b1101 #
#988000000
b1110 !
b1110 #
#990000000
b1111 !
b1111 #
#992000000
b0000 !
b0000 #
#994000000
b0001 !
1"
b0001 #
1$
#996000000
b0010 !
0"
b0010 #
0$
#998000000
b0011 !
1"
b0011 #
1$
#1000000000
b0100 !
0"
b0100 #
0$
