problems/problem_5_2_2.vhd
LIBRARY ieee;
USE ieee.std_logic_1164.ALL;
USE ieee.numeric_std.ALL;
USE ieee.math_real.ALL;

ENTITY problem_5_2_3 IS
    PORT (
        abcd : IN STD_LOGIC_VECTOR(3 DOWNTO 0);
        f : OUT STD_LOGIC
    );
END ENTITY problem_5_2_3;

ARCHITECTURE rtl OF problem_5_2_3 IS
BEGIN

    PROCESS (abcd)
    BEGIN

        CASE abcd IS
            WHEN "0001" | "0011" | "1001" | "1011" =>
                F <= '1';
            WHEN OTHERS =>
                F <= '0';

        END CASE;
    END PROCESS;
END ARCHITECTURE;

problems/problem_5_2_3_test.vhd
LIBRARY IEEE;
USE IEEE.STD_LOGIC_1164.ALL;
USE IEEE.STD_LOGIC_ARITH.ALL;
USE IEEE.STD_LOGIC_UNSIGNED.ALL;
USE IEEE.NUMERIC_STD.ALL;

ENTITY problem_5_2_3_test IS
END problem_5_2_3_test;

ARCHITECTURE behavior OF problem_5_2_3_test IS

    SIGNAL abcd : STD_LOGIC_VECTOR(3 DOWNTO 0) := (OTHERS => '0');
    SIGNAL f : STD_LOGIC := '0';

BEGIN
    UUT : ENTITY work.problem_5_2_3 PORT MAP(abcd, f);
    tb : PROCESS
    BEGIN
        FOR j IN 0 TO 2 ** abcd'length - 1 LOOP
            abcd <= STD_LOGIC_VECTOR(to_unsigned(j, abcd'length));
            WAIT FOR 2 ns;
        END LOOP;
    END PROCESS tb;
END;

waves/problem_5_2_3_test.vcd
$date
  Mon May 16 09:47:14 2022
$end
$version
  GHDL v0
$end
$timescale
  1 fs
$end
$scope module standard $end
$upscope $end
$scope module textio $end
$upscope $end
$scope module std_logic_1164 $end
$upscope $end
$scope module std_logic_arith $end
$upscope $end
$scope module std_logic_unsigned $end
$upscope $end
$scope module numeric_std $end
$upscope $end
$scope module math_real $end
$upscope $end
$scope module problem_5_2_3_test $end
$var reg 4 ! abcd[3:0] $end
$var reg 1 " f $end
$scope module uut $end
$var reg 4 # abcd[3:0] $end
$var reg 1 $ f $end
$upscope $end
$upscope $end
$enddefinitions $end
#0
b0000 !
0"
b0000 #
0$
#2000000
b0001 !
b0001 #
#4000000
b0010 !
b0010 #
#6000000
b0011 !
b0011 #
#8000000
b0100 !
1"
b0100 #
1$
#10000000
b0101 !
b0101 #
#12000000
b0110 !
0"
b0110 #
0$
#14000000
b0111 !
1"
b0111 #
1$
#16000000
b1000 !
0"
b1000 #
0$
#18000000
b1001 !
b1001 #
#20000000
b1010 !
b1010 #
#22000000
b1011 !
b1011 #
#24000000
b1100 !
1"
b1100 #
1$
#26000000
b1101 !
b1101 #
#28000000
b1110 !
0"
b1110 #
0$
#30000000
b1111 !
1"
b1111 #
1$
#32000000
b0000 !
0"
b0000 #
0$
#34000000
b0001 !
b0001 #
#36000000
b0010 !
b0010 #
#38000000
b0011 !
b0011 #
#40000000
b0100 !
1"
b0100 #
1$
#42000000
b0101 !
b0101 #
#44000000
b0110 !
0"
b0110 #
0$
#46000000
b0111 !
1"
b0111 #
1$
#48000000
b1000 !
0"
b1000 #
0$
#50000000
b1001 !
b1001 #
#52000000
b1010 !
b1010 #
#54000000
b1011 !
b1011 #
#56000000
b1100 !
1"
b1100 #
1$
#58000000
b1101 !
b1101 #
#60000000
b1110 !
0"
b1110 #
0$
#62000000
b1111 !
1"
b1111 #
1$
#64000000
b0000 !
0"
b0000 #
0$
#66000000
b0001 !
b0001 #
#68000000
b0010 !
b0010 #
#70000000
b0011 !
b0011 #
#72000000
b0100 !
1"
b0100 #
1$
#74000000
b0101 !
b0101 #
#76000000
b0110 !
0"
b0110 #
0$
#78000000
b0111 !
1"
b0111 #
1$
#80000000
b1000 !
0"
b1000 #
0$
#82000000
b1001 !
b1001 #
#84000000
b1010 !
b1010 #
#86000000
b1011 !
b1011 #
#88000000
b1100 !
1"
b1100 #
1$
#90000000
b1101 !
b1101 #
#92000000
b1110 !
0"
b1110 #
0$
#94000000
b1111 !
1"
b1111 #
1$
#96000000
b0000 !
0"
b0000 #
0$
#98000000
b0001 !
b0001 #
#100000000
b0010 !
b0010 #
#102000000
b0011 !
b0011 #
#104000000
b0100 !
1"
b0100 #
1$
#106000000
b0101 !
b0101 #
#108000000
b0110 !
0"
b0110 #
0$
#110000000
b0111 !
1"
b0111 #
1$
#112000000
b1000 !
0"
b1000 #
0$
#114000000
b1001 !
b1001 #
#116000000
b1010 !
b1010 #
#118000000
b1011 !
b1011 #
#120000000
b1100 !
1"
b1100 #
1$
#122000000
b1101 !
b1101 #
#124000000
b1110 !
0"
b1110 #
0$
#126000000
b1111 !
1"
b1111 #
1$
#128000000
b0000 !
0"
b0000 #
0$
#130000000
b0001 !
b0001 #
#132000000
b0010 !
b0010 #
#134000000
b0011 !
b0011 #
#136000000
b0100 !
1"
b0100 #
1$
#138000000
b0101 !
b0101 #
#140000000
b0110 !
0"
b0110 #
0$
#142000000
b0111 !
1"
b0111 #
1$
#144000000
b1000 !
0"
b1000 #
0$
#146000000
b1001 !
b1001 #
#148000000
b1010 !
b1010 #
#150000000
b1011 !
b1011 #
#152000000
b1100 !
1"
b1100 #
1$
#154000000
b1101 !
b1101 #
#156000000
b1110 !
0"
b1110 #
0$
#158000000
b1111 !
1"
b1111 #
1$
#160000000
b0000 !
0"
b0000 #
0$
#162000000
b0001 !
b0001 #
#164000000
b0010 !
b0010 #
#166000000
b0011 !
b0011 #
#168000000
b0100 !
1"
b0100 #
1$
#170000000
b0101 !
b0101 #
#172000000
b0110 !
0"
b0110 #
0$
#174000000
b0111 !
1"
b0111 #
1$
#176000000
b1000 !
0"
b1000 #
0$
#178000000
b1001 !
b1001 #
#180000000
b1010 !
b1010 #
#182000000
b1011 !
b1011 #
#184000000
b1100 !
1"
b1100 #
1$
#186000000
b1101 !
b1101 #
#188000000
b1110 !
0"
b1110 #
0$
#190000000
b1111 !
1"
b1111 #
1$
#192000000
b0000 !
0"
b0000 #
0$
#194000000
b0001 !
b0001 #
#196000000
b0010 !
b0010 #
#198000000
b0011 !
b0011 #
#200000000
b0100 !
1"
b0100 #
1$
#202000000
b0101 !
b0101 #
#204000000
b0110 !
0"
b0110 #
0$
#206000000
b0111 !
1"
b0111 #
1$
#208000000
b1000 !
0"
b1000 #
0$
#210000000
b1001 !
b1001 #
#212000000
b1010 !
b1010 #
#214000000
b1011 !
b1011 #
#216000000
b1100 !
1"
b1100 #
1$
#218000000
b1101 !
b1101 #
#220000000
b1110 !
0"
b1110 #
0$
#222000000
b1111 !
1"
b1111 #
1$
#224000000
b0000 !
0"
b0000 #
0$
#226000000
b0001 !
b0001 #
#228000000
b0010 !
b0010 #
#230000000
b0011 !
b0011 #
#232000000
b0100 !
1"
b0100 #
1$
#234000000
b0101 !
b0101 #
#236000000
b0110 !
0"
b0110 #
0$
#238000000
b0111 !
1"
b0111 #
1$
#240000000
b1000 !
0"
b1000 #
0$
#242000000
b1001 !
b1001 #
#244000000
b1010 !
b1010 #
#246000000
b1011 !
b1011 #
#248000000
b1100 !
1"
b1100 #
1$
#250000000
b1101 !
b1101 #
#252000000
b1110 !
0"
b1110 #
0$
#254000000
b1111 !
1"
b1111 #
1$
#256000000
b0000 !
0"
b0000 #
0$
#258000000
b0001 !
b0001 #
#260000000
b0010 !
b0010 #
#262000000
b0011 !
b0011 #
#264000000
b0100 !
1"
b0100 #
1$
#266000000
b0101 !
b0101 #
#268000000
b0110 !
0"
b0110 #
0$
#270000000
b0111 !
1"
b0111 #
1$
#272000000
b1000 !
0"
b1000 #
0$
#274000000
b1001 !
b1001 #
#276000000
b1010 !
b1010 #
#278000000
b1011 !
b1011 #
#280000000
b1100 !
1"
b1100 #
1$
#282000000
b1101 !
b1101 #
#284000000
b1110 !
0"
b1110 #
0$
#286000000
b1111 !
1"
b1111 #
1$
#288000000
b0000 !
0"
b0000 #
0$
#290000000
b0001 !
b0001 #
#292000000
b0010 !
b0010 #
#294000000
b0011 !
b0011 #
#296000000
b0100 !
1"
b0100 #
1$
#298000000
b0101 !
b0101 #
#300000000
b0110 !
0"
b0110 #
0$
#302000000
b0111 !
1"
b0111 #
1$
#304000000
b1000 !
0"
b1000 #
0$
#306000000
b1001 !
b1001 #
#308000000
b1010 !
b1010 #
#310000000
b1011 !
b1011 #
#312000000
b1100 !
1"
b1100 #
1$
#314000000
b1101 !
b1101 #
#316000000
b1110 !
0"
b1110 #
0$
#318000000
b1111 !
1"
b1111 #
1$
#320000000
b0000 !
0"
b0000 #
0$
#322000000
b0001 !
b0001 #
#324000000
b0010 !
b0010 #
#326000000
b0011 !
b0011 #
#328000000
b0100 !
1"
b0100 #
1$
#330000000
b0101 !
b0101 #
#332000000
b0110 !
0"
b0110 #
0$
#334000000
b0111 !
1"
b0111 #
1$
#336000000
b1000 !
0"
b1000 #
0$
#338000000
b1001 !
b1001 #
#340000000
b1010 !
b1010 #
#342000000
b1011 !
b1011 #
#344000000
b1100 !
1"
b1100 #
1$
#346000000
b1101 !
b1101 #
#348000000
b1110 !
0"
b1110 #
0$
#350000000
b1111 !
1"
b1111 #
1$
#352000000
b0000 !
0"
b0000 #
0$
#354000000
b0001 !
b0001 #
#356000000
b0010 !
b0010 #
#358000000
b0011 !
b0011 #
#360000000
b0100 !
1"
b0100 #
1$
#362000000
b0101 !
b0101 #
#364000000
b0110 !
0"
b0110 #
0$
#366000000
b0111 !
1"
b0111 #
1$
#368000000
b1000 !
0"
b1000 #
0$
#370000000
b1001 !
b1001 #
#372000000
b1010 !
b1010 #
#374000000
b1011 !
b1011 #
#376000000
b1100 !
1"
b1100 #
1$
#378000000
b1101 !
b1101 #
#380000000
b1110 !
0"
b1110 #
0$
#382000000
b1111 !
1"
b1111 #
1$
#384000000
b0000 !
0"
b0000 #
0$
#386000000
b0001 !
b0001 #
#388000000
b0010 !
b0010 #
#390000000
b0011 !
b0011 #
#392000000
b0100 !
1"
b0100 #
1$
#394000000
b0101 !
b0101 #
#396000000
b0110 !
0"
b0110 #
0$
#398000000
b0111 !
1"
b0111 #
1$
#400000000
b1000 !
0"
b1000 #
0$
#402000000
b1001 !
b1001 #
#404000000
b1010 !
b1010 #
#406000000
b1011 !
b1011 #
#408000000
b1100 !
1"
b1100 #
1$
#410000000
b1101 !
b1101 #
#412000000
b1110 !
0"
b1110 #
0$
#414000000
b1111 !
1"
b1111 #
1$
#416000000
b0000 !
0"
b0000 #
0$
#418000000
b0001 !
b0001 #
#420000000
b0010 !
b0010 #
#422000000
b0011 !
b0011 #
#424000000
b0100 !
1"
b0100 #
1$
#426000000
b0101 !
b0101 #
#428000000
b0110 !
0"
b0110 #
0$
#430000000
b0111 !
1"
b0111 #
1$
#432000000
b1000 !
0"
b1000 #
0$
#434000000
b1001 !
b1001 #
#436000000
b1010 !
b1010 #
#438000000
b1011 !
b1011 #
#440000000
b1100 !
1"
b1100 #
1$
#442000000
b1101 !
b1101 #
#444000000
b1110 !
0"
b1110 #
0$
#446000000
b1111 !
1"
b1111 #
1$
#448000000
b0000 !
0"
b0000 #
0$
#450000000
b0001 !
b0001 #
#452000000
b0010 !
b0010 #
#454000000
b0011 !
b0011 #
#456000000
b0100 !
1"
b0100 #
1$
#458000000
b0101 !
b0101 #
#460000000
b0110 !
0"
b0110 #
0$
#462000000
b0111 !
1"
b0111 #
1$
#464000000
b1000 !
0"
b1000 #
0$
#466000000
b1001 !
b1001 #
#468000000
b1010 !
b1010 #
#470000000
b1011 !
b1011 #
#472000000
b1100 !
1"
b1100 #
1$
#474000000
b1101 !
b1101 #
#476000000
b1110 !
0"
b1110 #
0$
#478000000
b1111 !
1"
b1111 #
1$
#480000000
b0000 !
0"
b0000 #
0$
#482000000
b0001 !
b0001 #
#484000000
b0010 !
b0010 #
#486000000
b0011 !
b0011 #
#488000000
b0100 !
1"
b0100 #
1$
#490000000
b0101 !
b0101 #
#492000000
b0110 !
0"
b0110 #
0$
#494000000
b0111 !
1"
b0111 #
1$
#496000000
b1000 !
0"
b1000 #
0$
#498000000
b1001 !
b1001 #
#500000000
b1010 !
b1010 #
#502000000
b1011 !
b1011 #
#504000000
b1100 !
1"
b1100 #
1$
#506000000
b1101 !
b1101 #
#508000000
b1110 !
0"
b1110 #
0$
#510000000
b1111 !
1"
b1111 #
1$
#512000000
b0000 !
0"
b0000 #
0$
#514000000
b0001 !
b0001 #
#516000000
b0010 !
b0010 #
#518000000
b0011 !
b0011 #
#520000000
b0100 !
1"
b0100 #
1$
#522000000
b0101 !
b0101 #
#524000000
b0110 !
0"
b0110 #
0$
#526000000
b0111 !
1"
b0111 #
1$
#528000000
b1000 !
0"
b1000 #
0$
#530000000
b1001 !
b1001 #
#532000000
b1010 !
b1010 #
#534000000
b1011 !
b1011 #
#536000000
b1100 !
1"
b1100 #
1$
#538000000
b1101 !
b1101 #
#540000000
b1110 !
0"
b1110 #
0$
#542000000
b1111 !
1"
b1111 #
1$
#544000000
b0000 !
0"
b0000 #
0$
#546000000
b0001 !
b0001 #
#548000000
b0010 !
b0010 #
#550000000
b0011 !
b0011 #
#552000000
b0100 !
1"
b0100 #
1$
#554000000
b0101 !
b0101 #
#556000000
b0110 !
0"
b0110 #
0$
#558000000
b0111 !
1"
b0111 #
1$
#560000000
b1000 !
0"
b1000 #
0$
#562000000
b1001 !
b1001 #
#564000000
b1010 !
b1010 #
#566000000
b1011 !
b1011 #
#568000000
b1100 !
1"
b1100 #
1$
#570000000
b1101 !
b1101 #
#572000000
b1110 !
0"
b1110 #
0$
#574000000
b1111 !
1"
b1111 #
1$
#576000000
b0000 !
0"
b0000 #
0$
#578000000
b0001 !
b0001 #
#580000000
b0010 !
b0010 #
#582000000
b0011 !
b0011 #
#584000000
b0100 !
1"
b0100 #
1$
#586000000
b0101 !
b0101 #
#588000000
b0110 !
0"
b0110 #
0$
#590000000
b0111 !
1"
b0111 #
1$
#592000000
b1000 !
0"
b1000 #
0$
#594000000
b1001 !
b1001 #
#596000000
b1010 !
b1010 #
#598000000
b1011 !
b1011 #
#600000000
b1100 !
1"
b1100 #
1$
#602000000
b1101 !
b1101 #
#604000000
b1110 !
0"
b1110 #
0$
#606000000
b1111 !
1"
b1111 #
1$
#608000000
b0000 !
0"
b0000 #
0$
#610000000
b0001 !
b0001 #
#612000000
b0010 !
b0010 #
#614000000
b0011 !
b0011 #
#616000000
b0100 !
1"
b0100 #
1$
#618000000
b0101 !
b0101 #
#620000000
b0110 !
0"
b0110 #
0$
#622000000
b0111 !
1"
b0111 #
1$
#624000000
b1000 !
0"
b1000 #
0$
#626000000
b1001 !
b1001 #
#628000000
b1010 !
b1010 #
#630000000
b1011 !
b1011 #
#632000000
b1100 !
1"
b1100 #
1$
#634000000
b1101 !
b1101 #
#636000000
b1110 !
0"
b1110 #
0$
#638000000
b1111 !
1"
b1111 #
1$
#640000000
b0000 !
0"
b0000 #
0$
#642000000
b0001 !
b0001 #
#644000000
b0010 !
b0010 #
#646000000
b0011 !
b0011 #
#648000000
b0100 !
1"
b0100 #
1$
#650000000
b0101 !
b0101 #
#652000000
b0110 !
0"
b0110 #
0$
#654000000
b0111 !
1"
b0111 #
1$
#656000000
b1000 !
0"
b1000 #
0$
#658000000
b1001 !
b1001 #
#660000000
b1010 !
b1010 #
#662000000
b1011 !
b1011 #
#664000000
b1100 !
1"
b1100 #
1$
#666000000
b1101 !
b1101 #
#668000000
b1110 !
0"
b1110 #
0$
#670000000
b1111 !
1"
b1111 #
1$
#672000000
b0000 !
0"
b0000 #
0$
#674000000
b0001 !
b0001 #
#676000000
b0010 !
b0010 #
#678000000
b0011 !
b0011 #
#680000000
b0100 !
1"
b0100 #
1$
#682000000
b0101 !
b0101 #
#684000000
b0110 !
0"
b0110 #
0$
#686000000
b0111 !
1"
b0111 #
1$
#688000000
b1000 !
0"
b1000 #
0$
#690000000
b1001 !
b1001 #
#692000000
b1010 !
b1010 #
#694000000
b1011 !
b1011 #
#696000000
b1100 !
1"
b1100 #
1$
#698000000
b1101 !
b1101 #
#700000000
b1110 !
0"
b1110 #
0$
#702000000
b1111 !
1"
b1111 #
1$
#704000000
b0000 !
0"
b0000 #
0$
#706000000
b0001 !
b0001 #
#708000000
b0010 !
b0010 #
#710000000
b0011 !
b0011 #
#712000000
b0100 !
1"
b0100 #
1$
#714000000
b0101 !
b0101 #
#716000000
b0110 !
0"
b0110 #
0$
#718000000
b0111 !
1"
b0111 #
1$
#720000000
b1000 !
0"
b1000 #
0$
#722000000
b1001 !
b1001 #
#724000000
b1010 !
b1010 #
#726000000
b1011 !
b1011 #
#728000000
b1100 !
1"
b1100 #
1$
#730000000
b1101 !
b1101 #
#732000000
b1110 !
0"
b1110 #
0$
#734000000
b1111 !
1"
b1111 #
1$
#736000000
b0000 !
0"
b0000 #
0$
#738000000
b0001 !
b0001 #
#740000000
b0010 !
b0010 #
#742000000
b0011 !
b0011 #
#744000000
b0100 !
1"
b0100 #
1$
#746000000
b0101 !
b0101 #
#748000000
b0110 !
0"
b0110 #
0$
#750000000
b0111 !
1"
b0111 #
1$
#752000000
b1000 !
0"
b1000 #
0$
#754000000
b1001 !
b1001 #
#756000000
b1010 !
b1010 #
#758000000
b1011 !
b1011 #
#760000000
b1100 !
1"
b1100 #
1$
#762000000
b1101 !
b1101 #
#764000000
b1110 !
0"
b1110 #
0$
#766000000
b1111 !
1"
b1111 #
1$
#768000000
b0000 !
0"
b0000 #
0$
#770000000
b0001 !
b0001 #
#772000000
b0010 !
b0010 #
#774000000
b0011 !
b0011 #
#776000000
b0100 !
1"
b0100 #
1$
#778000000
b0101 !
b0101 #
#780000000
b0110 !
0"
b0110 #
0$
#782000000
b0111 !
1"
b0111 #
1$
#784000000
b1000 !
0"
b1000 #
0$
#786000000
b1001 !
b1001 #
#788000000
b1010 !
b1010 #
#790000000
b1011 !
b1011 #
#792000000
b1100 !
1"
b1100 #
1$
#794000000
b1101 !
b1101 #
#796000000
b1110 !
0"
b1110 #
0$
#798000000
b1111 !
1"
b1111 #
1$
#800000000
b0000 !
0"
b0000 #
0$
#802000000
b0001 !
b0001 #
#804000000
b0010 !
b0010 #
#806000000
b0011 !
b0011 #
#808000000
b0100 !
1"
b0100 #
1$
#810000000
b0101 !
b0101 #
#812000000
b0110 !
0"
b0110 #
0$
#814000000
b0111 !
1"
b0111 #
1$
#816000000
b1000 !
0"
b1000 #
0$
#818000000
b1001 !
b1001 #
#820000000
b1010 !
b1010 #
#822000000
b1011 !
b1011 #
#824000000
b1100 !
1"
b1100 #
1$
#826000000
b1101 !
b1101 #
#828000000
b1110 !
0"
b1110 #
0$
#830000000
b1111 !
1"
b1111 #
1$
#832000000
b0000 !
0"
b0000 #
0$
#834000000
b0001 !
b0001 #
#836000000
b0010 !
b0010 #
#838000000
b0011 !
b0011 #
#840000000
b0100 !
1"
b0100 #
1$
#842000000
b0101 !
b0101 #
#844000000
b0110 !
0"
b0110 #
0$
#846000000
b0111 !
1"
b0111 #
1$
#848000000
b1000 !
0"
b1000 #
0$
#850000000
b1001 !
b1001 #
#852000000
b1010 !
b1010 #
#854000000
b1011 !
b1011 #
#856000000
b1100 !
1"
b1100 #
1$
#858000000
b1101 !
b1101 #
#860000000
b1110 !
0"
b1110 #
0$
#862000000
b1111 !
1"
b1111 #
1$
#864000000
b0000 !
0"
b0000 #
0$
#866000000
b0001 !
b0001 #
#868000000
b0010 !
b0010 #
#870000000
b0011 !
b0011 #
#872000000
b0100 !
1"
b0100 #
1$
#874000000
b0101 !
b0101 #
#876000000
b0110 !
0"
b0110 #
0$
#878000000
b0111 !
1"
b0111 #
1$
#880000000
b1000 !
0"
b1000 #
0$
#882000000
b1001 !
b1001 #
#884000000
b1010 !
b1010 #
#886000000
b1011 !
b1011 #
#888000000
b1100 !
1"
b1100 #
1$
#890000000
b1101 !
b1101 #
#892000000
b1110 !
0"
b1110 #
0$
#894000000
b1111 !
1"
b1111 #
1$
#896000000
b0000 !
0"
b0000 #
0$
#898000000
b0001 !
b0001 #
#900000000
b0010 !
b0010 #
#902000000
b0011 !
b0011 #
#904000000
b0100 !
1"
b0100 #
1$
#906000000
b0101 !
b0101 #
#908000000
b0110 !
0"
b0110 #
0$
#910000000
b0111 !
1"
b0111 #
1$
#912000000
b1000 !
0"
b1000 #
0$
#914000000
b1001 !
b1001 #
#916000000
b1010 !
b1010 #
#918000000
b1011 !
b1011 #
#920000000
b1100 !
1"
b1100 #
1$
#922000000
b1101 !
b1101 #
#924000000
b1110 !
0"
b1110 #
0$
#926000000
b1111 !
1"
b1111 #
1$
#928000000
b0000 !
0"
b0000 #
0$
#930000000
b0001 !
b0001 #
#932000000
b0010 !
b0010 #
#934000000
b0011 !
b0011 #
#936000000
b0100 !
1"
b0100 #
1$
#938000000
b0101 !
b0101 #
#940000000
b0110 !
0"
b0110 #
0$
#942000000
b0111 !
1"
b0111 #
1$
#944000000
b1000 !
0"
b1000 #
0$
#946000000
b1001 !
b1001 #
#948000000
b1010 !
b1010 #
#950000000
b1011 !
b1011 #
#952000000
b1100 !
1"
b1100 #
1$
#954000000
b1101 !
b1101 #
#956000000
b1110 !
0"
b1110 #
0$
#958000000
b1111 !
1"
b1111 #
1$
#960000000
b0000 !
0"
b0000 #
0$
#962000000
b0001 !
b0001 #
#964000000
b0010 !
b0010 #
#966000000
b0011 !
b0011 #
#968000000
b0100 !
1"
b0100 #
1$
#970000000
b0101 !
b0101 #
#972000000
b0110 !
0"
b0110 #
0$
#974000000
b0111 !
1"
b0111 #
1$
#976000000
b1000 !
0"
b1000 #
0$
#978000000
b1001 !
b1001 #
#980000000
b1010 !
b1010 #
#982000000
b1011 !
b1011 #
#984000000
b1100 !
1"
b1100 #
1$
#986000000
b1101 !
b1101 #
#988000000
b1110 !
0"
b1110 #
0$
#990000000
b1111 !
1"
b1111 #
1$
#992000000
b0000 !
0"
b0000 #
0$
#994000000
b0001 !
b0001 #
#996000000
b0010 !
b0010 #
#998000000
b0011 !
b0011 #
#1000000000
b0100 !
1"
b0100 #
1$
