decoder/dec3x8_concurrent.vhd
--libraries to be used are specified here
library IEEE;
use IEEE.STD_LOGIC_1164.ALL;

--entity declaration with port definitions
entity dec3x8_concurrent is
port(    input :        in std_logic_vector(2 downto 0);  --3 bit input
         output : out std_logic_vector(7 downto 0)  -- 8 bit ouput
   );
end dec3x8_concurrent;
--architecture of entity
architecture Behavioral of dec3x8_concurrent is

begin 
output(0) <= (not input(2)) and (not input(1)) and (not input(0));
output(1) <= (not input(2)) and (not input(1)) and input(0);
output(2) <= (not input(2)) and input(1) and (not input(0));
output(3) <= (not input(2)) and input(1) and input(0);
output(4) <= input(2) and (not input(1)) and (not input(0));
output(5) <= input(2) and (not input(1)) and input(0);
output(6) <= input(2) and input(1) and (not input(0));
output(7) <= input(2) and input(1) and input(0);

end Behavioral;

decoder/dec3x8_concurrent.test.vhd
library IEEE;
use IEEE.STD_LOGIC_1164.ALL;


--this is how entity for your test bench code has to be declared.
entity testbench is
end testbench;

architecture behavior of testbench is
--signal declarations.
signal input : std_logic_vector(2 downto 0) :=(others => '0');
signal output :  std_logic_vector(7 downto 0) :=(others => '0');

begin
--entity instantiation
UUT : entity work.dec3x8_concurrent port map(input,output);

--definition of simulation process
tb : process 
begin
input<="000";  --input = 0.
wait for 2 ns;
input<="001";   --input = 1.
wait for 2 ns;
input<="010";   --input = 2.
wait for 2 ns;
input<="011";   --input = 3.
wait for 2 ns;
input<="100";   --input = 4.
wait for 2 ns;
input<="101";   --input = 5.
wait for 2 ns;
input<="110";   --input = 6.
wait for 2 ns;
input<="111";   --input = 7.
wait;
end process tb;

end;

decoder/testbench.vcd
$date
  Fri Mar 11 23:34:16 2022
$end
$version
  GHDL v0
$end
$timescale
  1 fs
$end
$scope module standard $end
$upscope $end
$scope module textio $end
$upscope $end
$scope module std_logic_1164 $end
$upscope $end
$scope module testbench $end
$var reg 3 ! input[2:0] $end
$var reg 8 " output[7:0] $end
$scope module uut $end
$var reg 3 # input[2:0] $end
$var reg 8 $ output[7:0] $end
$upscope $end
$upscope $end
$enddefinitions $end
#0
b000 !
b00000001 "
b000 #
b00000001 $
#2000000
b001 !
b00000010 "
b001 #
b00000010 $
#4000000
b010 !
b00000100 "
b010 #
b00000100 $
#6000000
b011 !
b00001000 "
b011 #
b00001000 $
#8000000
b100 !
b00010000 "
b100 #
b00010000 $
#10000000
b101 !
b00100000 "
b101 #
b00100000 $
#12000000
b110 !
b01000000 "
b110 #
b01000000 $
#14000000
b111 !
b10000000 "
b111 #
b10000000 $
